{
  "_id": "Pk3Ht0KZyFxSeL07",
  "img": "systems/pf2e/icons/features/classes/keen-flair.webp",
  "name": "Keen Flair",
  "system": {
    "description": {
      "gm": "",
      "value": "<p>You inflict particularly devastating attacks on even well-defended foes. When you Strike with a weapon or unarmed attack with which you have master proficiency, if you roll a 19 on the die and the roll is a success, you critically succeed instead.</p>"
    },
    "rules": [
      {
        "adjustment": {
          "success": "to-critical-success"
        },
        "key": "AdjustDegreeOfSuccess",
        "predicate": [
          "check:roll:total:natural:19",
          "item:proficiency:rank:3"
        ],
        "selector": "strike-attack-roll"
      }
    ],
    "slug": "keen-flair",
    "_migration": {
      "version": 0.935,
      "lastMigration": null,
      "previous": {
        "schema": 0.879,
        "foundry": "12.331",
        "system": "6.7.2"
      }
    },
    "traits": {
      "otherTags": [],
      "value": [
        "swashbuckler"
      ],
      "rarity": "common"
    },
    "publication": {
      "title": "Pathfinder Advanced Player's Guide",
      "authors": "",
      "license": "OGL",
      "remaster": false
    },
    "level": {
      "value": 15
    },
    "category": "classfeature",
    "onlyLevel1": false,
    "maxTakable": 1,
    "actionType": {
      "value": "passive"
    },
    "actions": {
      "value": null
    },
    "prerequisites": {
      "value": []
    },
    "location": null
  },
  "type": "feat",
  "flags": {
    "core": {
      "sourceId": "Compendium.pf2e.classfeatures.Item.Pk3Ht0KZyFxSeL07"
    }
  },
  "effects": [],
  "_stats": {
    "coreVersion": "12.331",
    "systemId": "pf2e",
    "systemVersion": "6.7.2",
    "compendiumSource": "Compendium.pf2e-legacy-content.class-features-legacy.Item.Pk3Ht0KZyFxSeL07",
    "duplicateSource": null
  },
  "folder": null,
  "sort": 0,
  "ownership": {
    "default": 0
  },
  "_key": "!items!Pk3Ht0KZyFxSeL07"
}
