{
  "_id": "U74JoAcLHTOsZG6q",
  "img": "systems/pf2e/icons/features/classes/swashbuckler-expertise.webp",
  "name": "Swashbuckler Expertise",
  "system": {
    "description": {
      "gm": "",
      "value": "<p>You perform swashbuckling techniques with exceptional flair, making them harder to resist. Your proficiency rank for your swashbuckler class DC increases to expert.</p>"
    },
    "rules": [
      {
        "key": "ActiveEffectLike",
        "mode": "upgrade",
        "path": "system.proficiencies.classDCs.swashbuckler.rank",
        "value": 2
      }
    ],
    "slug": "swashbuckler-expertise",
    "_migration": {
      "version": 0.935,
      "lastMigration": null,
      "previous": {
        "schema": 0.879,
        "foundry": "12.331",
        "system": "6.7.2"
      }
    },
    "traits": {
      "otherTags": [],
      "value": [
        "swashbuckler"
      ],
      "rarity": "common"
    },
    "publication": {
      "title": "Pathfinder Advanced Player's Guide",
      "authors": "",
      "license": "OGL",
      "remaster": false
    },
    "level": {
      "value": 9
    },
    "category": "classfeature",
    "onlyLevel1": false,
    "maxTakable": 1,
    "actionType": {
      "value": "passive"
    },
    "actions": {
      "value": null
    },
    "prerequisites": {
      "value": []
    },
    "location": null
  },
  "type": "feat",
  "flags": {
    "core": {
      "sourceId": "Compendium.pf2e.classfeatures.Item.U74JoAcLHTOsZG6q"
    }
  },
  "effects": [],
  "_stats": {
    "coreVersion": "12.331",
    "systemId": "pf2e",
    "systemVersion": "6.7.2",
    "compendiumSource": "Compendium.pf2e-legacy-content.class-features-legacy.Item.U74JoAcLHTOsZG6q",
    "duplicateSource": null
  },
  "folder": null,
  "sort": 0,
  "ownership": {
    "default": 0
  },
  "_key": "!items!U74JoAcLHTOsZG6q"
}
