{
  "_id": "BUHV5rev5HVgCrUB",
  "img": "systems/pf2e/icons/equipment/shields/precious-material-shields/darkwood-buckler.webp",
  "name": "Darkwood Buckler (Standard-Grade)",
  "system": {
    "description": {
      "gm": "",
      "value": "<p>Duskwood shields are 1 Bulk lighter than normal (or light Bulk if their normal Bulk is 1, with no effect on a shield that normally has light Bulk).</p>\n<p>The shield has Hardness 3, HP 12, and BT 6.</p>\n<hr />\n<p><strong>Craft Requirements</strong> duskwood worth at least 50 gp</p>"
    },
    "rules": [],
    "slug": "duskwood-buckler-standard-grade",
    "_migration": {
      "version": 0.935,
      "lastMigration": null,
      "previous": {
        "schema": 0.879,
        "foundry": "12.331",
        "system": "6.7.2"
      }
    },
    "traits": {
      "otherTags": [],
      "value": [],
      "rarity": "uncommon",
      "integrated": null
    },
    "publication": {
      "title": "Pathfinder Core Rulebook",
      "authors": "",
      "license": "OGL",
      "remaster": false
    },
    "level": {
      "value": 8
    },
    "quantity": 1,
    "baseItem": null,
    "bulk": {
      "value": 0.1
    },
    "hp": {
      "value": 12,
      "max": 12
    },
    "hardness": 3,
    "price": {
      "value": {
        "gp": 400
      }
    },
    "equipped": {
      "carryType": "worn",
      "invested": null,
      "handsHeld": 0
    },
    "containerId": null,
    "size": "med",
    "material": {
      "type": "duskwood",
      "grade": "standard"
    },
    "identification": {
      "status": "identified",
      "unidentified": {
        "name": "",
        "img": "",
        "data": {
          "description": {
            "value": ""
          }
        }
      },
      "misidentified": {}
    },
    "acBonus": 1,
    "speedPenalty": 0,
    "runes": {
      "potency": 0,
      "resilient": 0,
      "property": [],
      "reinforcing": 0
    },
    "subitems": []
  },
  "type": "shield",
  "flags": {
    "core": {
      "sourceId": "Compendium.pf2e.equipment-srd.Item.BUHV5rev5HVgCrUB"
    }
  },
  "effects": [],
  "_stats": {
    "coreVersion": "12.331",
    "systemId": "pf2e",
    "systemVersion": "6.7.2",
    "compendiumSource": "Compendium.pf2e-legacy-content.equipment-legacy.Item.BUHV5rev5HVgCrUB",
    "duplicateSource": null
  },
  "folder": null,
  "sort": 0,
  "ownership": {
    "default": 0
  },
  "_key": "!items!BUHV5rev5HVgCrUB"
}
