{
  "_id": "SatFUtE2UaPvC394",
  "img": "icons/weapons/swords/greatsword-crossguard-silver.webp",
  "name": "Skyrider Sword",
  "system": {
    "description": {
      "gm": "",
      "value": "<p>This <em>+2 greater striking shock greatsword</em> has a broad, flat blade that can support the weight of a Medium-sized or smaller wielder. Magic allows the weapon to soar through the air, carrying its wielder along with it.</p>\n<hr />\n<p><strong>Activate</strong> <span class=\"action-glyph\">1</span> command</p>\n<p><strong>Frequency</strong> once per day</p>\n<p><strong>Requirements</strong> You're holding the sword in at least one hand</p>\n<hr />\n<p><strong>Effect</strong> You leap upon your sword as it soars through the air for up to 10 minutes. You gain a fly Speed of 25 feet or your land Speed, whichever is slower, but you can't Strike with your weapon except via the weapon's other activation (see below). You can Dismiss the activation, and it ends automatically if you cease holding the weapon with at least one hand.</p>\n<p>@UUID[Compendium.pf2e.equipment-effects.Item.Nbgf8zvHimdQqIu6]{Effect: Skyrider Sword}</p>\n<hr />\n<p><strong>Activate</strong> <span class=\"action-glyph\">2</span> Interact</p>\n<p><strong>Requirements</strong> You are riding on your weapon</p>\n<hr />\n<p><strong>Effect</strong> You ride your weapon into a foe, attacking it as you fly past. You Fly, making a melee Strike with the weapon once at any point during your movement.</p>"
    },
    "rules": [],
    "slug": "skyrider-sword",
    "_migration": {
      "version": 0.935,
      "lastMigration": null,
      "previous": {
        "schema": 0.879,
        "foundry": "12.331",
        "system": "6.7.2"
      }
    },
    "traits": {
      "otherTags": [],
      "value": [
        "air",
        "magical",
        "versatile-p"
      ],
      "rarity": "uncommon"
    },
    "publication": {
      "title": "Pathfinder Lost Omens: The Grand Bazaar",
      "authors": "",
      "license": "OGL",
      "remaster": false
    },
    "level": {
      "value": 14
    },
    "quantity": 1,
    "baseItem": "greatsword",
    "bulk": {
      "value": 2
    },
    "hp": {
      "value": 0,
      "max": 0
    },
    "hardness": 0,
    "price": {
      "value": {
        "gp": 4500
      }
    },
    "equipped": {
      "carryType": "worn",
      "invested": null,
      "handsHeld": 0
    },
    "containerId": null,
    "size": "med",
    "material": {
      "type": null,
      "grade": null
    },
    "identification": {
      "status": "identified",
      "unidentified": {
        "name": "",
        "img": "",
        "data": {
          "description": {
            "value": ""
          }
        }
      },
      "misidentified": {}
    },
    "usage": {
      "value": "held-in-two-hands"
    },
    "category": "martial",
    "group": "sword",
    "bonus": {
      "value": 0
    },
    "damage": {
      "dice": 1,
      "die": "d12",
      "damageType": "slashing",
      "persistent": null
    },
    "bonusDamage": {
      "value": 0
    },
    "splashDamage": {
      "value": 0
    },
    "range": null,
    "reload": {
      "value": ""
    },
    "runes": {
      "potency": 2,
      "striking": 2,
      "property": [
        "shock"
      ]
    },
    "specific": {
      "material": {
        "type": null,
        "grade": null
      },
      "runes": {
        "potency": 2,
        "striking": 2,
        "property": [
          "shock"
        ]
      }
    },
    "subitems": [],
    "property1": {
      "value": "",
      "dice": 0,
      "die": "",
      "damageType": "",
      "critDice": 0,
      "critDie": "",
      "critDamage": "",
      "critDamageType": ""
    }
  },
  "type": "weapon",
  "flags": {
    "core": {
      "sourceId": "Compendium.pf2e.equipment-srd.Item.SatFUtE2UaPvC394"
    }
  },
  "effects": [],
  "_stats": {
    "coreVersion": "12.331",
    "systemId": "pf2e",
    "systemVersion": "6.7.2",
    "compendiumSource": "Compendium.pf2e-legacy-content.equipment-legacy.Item.SatFUtE2UaPvC394",
    "duplicateSource": null
  },
  "folder": null,
  "sort": 0,
  "ownership": {
    "default": 0
  },
  "_key": "!items!SatFUtE2UaPvC394"
}
