{
  "_id": "nDZX25OwoN0Imrq6",
  "img": "systems/pf2e/icons/equipment/shields/specific-shields/sturdy-shield.webp",
  "name": "Sturdy Shield (Lesser)",
  "system": {
    "description": {
      "gm": "",
      "value": "<p>With a superior design and excellent craftsmanship, this steel shield has higher Hardness than its non-magical counterparts, making it harder to break and destroy.</p>\n<p>The shield has Hardness 10, HP 80, and BT 40.</p>"
    },
    "rules": [],
    "slug": "sturdy-shield-lesser",
    "_migration": {
      "version": 0.935,
      "lastMigration": null,
      "previous": {
        "schema": 0.879,
        "foundry": "12.331",
        "system": "6.7.2"
      }
    },
    "traits": {
      "otherTags": [],
      "value": [
        "magical"
      ],
      "rarity": "common",
      "integrated": null
    },
    "publication": {
      "title": "Pathfinder Core Rulebook",
      "authors": "",
      "license": "OGL",
      "remaster": false
    },
    "level": {
      "value": 7
    },
    "quantity": 1,
    "baseItem": "steel-shield",
    "bulk": {
      "value": 1
    },
    "hp": {
      "value": 80,
      "max": 80
    },
    "hardness": 10,
    "price": {
      "value": {
        "gp": 360
      }
    },
    "equipped": {
      "carryType": "worn",
      "invested": null,
      "handsHeld": 0
    },
    "containerId": null,
    "size": "med",
    "material": {
      "type": null,
      "grade": null
    },
    "identification": {
      "status": "identified",
      "unidentified": {
        "name": "",
        "img": "",
        "data": {
          "description": {
            "value": ""
          }
        }
      },
      "misidentified": {}
    },
    "acBonus": 2,
    "speedPenalty": 0,
    "runes": {
      "potency": 0,
      "resilient": 0,
      "property": [],
      "reinforcing": 0
    },
    "subitems": [],
    "specific": {
      "material": {
        "type": null,
        "grade": null
      },
      "runes": {
        "reinforcing": 0
      },
      "integrated": null
    }
  },
  "type": "shield",
  "flags": {
    "core": {
      "sourceId": "Compendium.pf2e.equipment-srd.Item.nDZX25OwoN0Imrq6"
    }
  },
  "effects": [],
  "_stats": {
    "coreVersion": "12.331",
    "systemId": "pf2e",
    "systemVersion": "6.7.2",
    "compendiumSource": "Compendium.pf2e-legacy-content.equipment-legacy.Item.nDZX25OwoN0Imrq6",
    "duplicateSource": null
  },
  "folder": null,
  "sort": 0,
  "ownership": {
    "default": 0
  },
  "_key": "!items!nDZX25OwoN0Imrq6"
}
