{
  "_id": "10ddNHYJJOvEhEFD",
  "img": "icons/commodities/bones/horn-engraved-vines-grey.webp",
  "name": "Whelming Scrimshaw",
  "system": {
    "description": {
      "gm": "",
      "value": "<p><strong>Activate</strong> <span class=\"action-glyph\"> 2</span> Interact</p>\n<hr />\n<p>An etching of some aquatic beast dragging a figure beneath the waves adorns the ivory of a whelming scrimshaw. When you Activate this item, you break it and choose one creature within 30 feet. The target must attempt a @Check[type:fortitude|dc:30] save; amphibious and aquatic creatures are immune.</p>\n<hr />\n<p><strong>Critical Success</strong> The creature is unaffected.</p>\n<p><strong>Success</strong> The target becomes @UUID[Compendium.pf2e.conditionitems.Item.fesd1n5eVhpCSS18]{Sickened 1} and unable to breathe until this sickened condition ends.</p>\n<p><strong>Failure</strong> As success, but @UUID[Compendium.pf2e.conditionitems.Item.fesd1n5eVhpCSS18]{Sickened 2}.</p>\n<p><strong>Critical Failure</strong> As success, but @UUID[Compendium.pf2e.conditionitems.Item.fesd1n5eVhpCSS18]{Sickened 3}.</p>"
    },
    "rules": [],
    "slug": "whelming-scrimshaw",
    "_migration": {
      "version": 0.935,
      "lastMigration": null,
      "previous": {
        "schema": 0.879,
        "foundry": "12.331",
        "system": "6.7.2"
      }
    },
    "traits": {
      "otherTags": [],
      "value": [
        "consumable",
        "magical"
      ],
      "rarity": "common"
    },
    "publication": {
      "title": "Pathfinder Treasure Vault",
      "authors": "",
      "license": "OGL",
      "remaster": false
    },
    "level": {
      "value": 13
    },
    "quantity": 1,
    "baseItem": null,
    "bulk": {
      "value": 0.1
    },
    "hp": {
      "value": 0,
      "max": 0
    },
    "hardness": 0,
    "price": {
      "value": {
        "gp": 500
      }
    },
    "equipped": {
      "carryType": "worn",
      "handsHeld": 0
    },
    "containerId": null,
    "size": "med",
    "material": {
      "type": null,
      "grade": null
    },
    "identification": {
      "status": "identified",
      "unidentified": {
        "name": "",
        "img": "",
        "data": {
          "description": {
            "value": ""
          }
        }
      },
      "misidentified": {}
    },
    "category": "other",
    "uses": {
      "value": 1,
      "max": 1,
      "autoDestroy": true
    },
    "damage": null,
    "usage": {
      "value": "held-in-one-hand"
    },
    "stackGroup": null,
    "spell": null
  },
  "type": "consumable",
  "flags": {
    "core": {
      "sourceId": "Compendium.pf2e.equipment-srd.Item.10ddNHYJJOvEhEFD"
    }
  },
  "effects": [],
  "_stats": {
    "coreVersion": "12.331",
    "systemId": "pf2e",
    "systemVersion": "6.7.2",
    "compendiumSource": "Compendium.pf2e-legacy-content.equipment-legacy.Item.10ddNHYJJOvEhEFD",
    "duplicateSource": null
  },
  "folder": null,
  "sort": 0,
  "ownership": {
    "default": 0
  },
  "_key": "!items!10ddNHYJJOvEhEFD"
}
