{
  "prototypeToken": {
    "displayName": 20,
    "displayBars": 20,
    "name": "Horned Archon",
    "actorLink": false,
    "appendNumber": false,
    "prependAdjective": false,
    "width": 1,
    "height": 1,
    "texture": {
      "src": "systems/pf2e/icons/default-icons/npc.svg",
      "anchorX": 0.5,
      "anchorY": 0.5,
      "offsetX": 0,
      "offsetY": 0,
      "fit": "contain",
      "scaleX": 1,
      "scaleY": 1,
      "rotation": 0,
      "tint": "#ffffff",
      "alphaThreshold": 0.75
    },
    "hexagonalShape": 0,
    "lockRotation": false,
    "rotation": 0,
    "alpha": 1,
    "disposition": -1,
    "bar1": {
      "attribute": "attributes.hp"
    },
    "bar2": {
      "attribute": null
    },
    "light": {
      "negative": false,
      "priority": 0,
      "alpha": 0.5,
      "angle": 360,
      "bright": 0,
      "color": null,
      "coloration": 1,
      "dim": 0,
      "attenuation": 0.5,
      "luminosity": 0.5,
      "saturation": 0,
      "contrast": 0,
      "shadows": 0,
      "animation": {
        "type": null,
        "speed": 5,
        "intensity": 5,
        "reverse": false
      },
      "darkness": {
        "min": 0,
        "max": 1
      }
    },
    "sight": {
      "enabled": false,
      "range": 0,
      "angle": 360,
      "visionMode": "basic",
      "color": null,
      "attenuation": 0.1,
      "brightness": 0,
      "saturation": 0,
      "contrast": 0
    },
    "detectionModes": [],
    "occludable": {
      "radius": 0
    },
    "ring": {
      "enabled": false,
      "colors": {
        "ring": null,
        "background": null
      },
      "effects": 1,
      "subject": {
        "scale": 1,
        "texture": null
      }
    },
    "flags": {
      "pf2e": {
        "linkToActorSize": true,
        "autoscale": true
      }
    },
    "randomImg": false
  },
  "_id": "iII08V0HlvWGWSmu",
  "img": "systems/pf2e/icons/default-icons/npc.svg",
  "items": [
    {
      "_id": "QnuvWppYTYaOJTUu",
      "img": "systems/pf2e/icons/default-icons/spellcastingEntry.svg",
      "name": "Divine Innate Spells",
      "sort": 100000,
      "system": {
        "description": {
          "gm": "",
          "value": ""
        },
        "rules": [],
        "slug": null,
        "_migration": {
          "version": 0.935,
          "lastMigration": null,
          "previous": {
            "schema": 0.932,
            "foundry": "12.331",
            "system": "6.7.2"
          }
        },
        "traits": {
          "otherTags": []
        },
        "publication": {
          "title": "",
          "authors": "",
          "license": "OGL",
          "remaster": false
        },
        "ability": {
          "value": "cha"
        },
        "spelldc": {
          "value": 13,
          "dc": 21,
          "mod": 0
        },
        "tradition": {
          "value": "divine"
        },
        "prepared": {
          "value": "innate"
        },
        "showSlotlessLevels": {
          "value": false
        },
        "proficiency": {
          "value": 0
        },
        "slots": {
          "slot0": {
            "prepared": [],
            "value": 0,
            "max": 0
          },
          "slot1": {
            "prepared": [],
            "value": 0,
            "max": 0
          },
          "slot2": {
            "prepared": [],
            "value": 0,
            "max": 0
          },
          "slot3": {
            "prepared": [],
            "value": 0,
            "max": 0
          },
          "slot4": {
            "prepared": [],
            "value": 0,
            "max": 0
          },
          "slot5": {
            "prepared": [],
            "value": 0,
            "max": 0
          },
          "slot6": {
            "prepared": [],
            "value": 0,
            "max": 0
          },
          "slot7": {
            "prepared": [],
            "value": 0,
            "max": 0
          },
          "slot8": {
            "prepared": [],
            "value": 0,
            "max": 0
          },
          "slot9": {
            "prepared": [],
            "value": 0,
            "max": 0
          },
          "slot10": {
            "prepared": [],
            "value": 0,
            "max": 0
          },
          "slot11": {
            "prepared": [],
            "value": 0,
            "max": 0
          }
        },
        "autoHeightenLevel": {
          "value": null
        }
      },
      "type": "spellcastingEntry",
      "_stats": {
        "compendiumSource": null,
        "duplicateSource": null,
        "coreVersion": "12.331",
        "systemId": "pf2e",
        "systemVersion": "6.7.2"
      },
      "effects": [],
      "folder": null,
      "ownership": {
        "default": 0
      },
      "flags": {},
      "_key": "!actors.items!iII08V0HlvWGWSmu.QnuvWppYTYaOJTUu"
    },
    {
      "_id": "PYlSwGscGRdPPJeE",
      "flags": {
        "core": {
          "sourceId": "Compendium.pf2e.spells-srd.Item.SwUiVavHKMWG7t5K"
        }
      },
      "img": "systems/pf2e/icons/spells/tongues.webp",
      "name": "Tongues (Constant)",
      "sort": 200000,
      "system": {
        "description": {
          "gm": "",
          "value": "<p>The target can understand all words regardless of language and also speak the languages of other creatures. When in a mixed group of creatures, each time the target speaks, it can choose a creature and speak in a language that creature understands, even if the target doesn't know what language that is.</p>\n<hr />\n<p><strong>Heightened (7th)</strong> The duration is 8 hours.</p>"
        },
        "rules": [],
        "slug": "tongues",
        "_migration": {
          "version": 0.935,
          "lastMigration": null,
          "previous": {
            "schema": 0.932,
            "foundry": "12.331",
            "system": "6.7.2"
          }
        },
        "traits": {
          "otherTags": [],
          "value": [
            "concentrate",
            "manipulate"
          ],
          "rarity": "uncommon",
          "traditions": [
            "arcane",
            "divine",
            "occult"
          ]
        },
        "publication": {
          "title": "Pathfinder Core Rulebook",
          "authors": "",
          "license": "OGL",
          "remaster": false
        },
        "level": {
          "value": 5
        },
        "requirements": "",
        "target": {
          "value": "1 creature"
        },
        "range": {
          "value": "touch"
        },
        "area": null,
        "time": {
          "value": "2"
        },
        "duration": {
          "value": "1 hour",
          "sustained": false
        },
        "damage": {},
        "defense": null,
        "cost": {
          "value": ""
        },
        "location": {
          "value": "QnuvWppYTYaOJTUu",
          "heightenedLevel": 5
        },
        "counteraction": false
      },
      "type": "spell",
      "_stats": {
        "compendiumSource": "Compendium.pf2e.spells-srd.Item.SwUiVavHKMWG7t5K",
        "duplicateSource": null,
        "coreVersion": "12.331",
        "systemId": "pf2e",
        "systemVersion": "6.7.2"
      },
      "effects": [],
      "folder": null,
      "ownership": {
        "default": 0
      },
      "_key": "!actors.items!iII08V0HlvWGWSmu.PYlSwGscGRdPPJeE"
    },
    {
      "_id": "pADzomLeub6qyUdT",
      "flags": {
        "core": {
          "sourceId": "Compendium.pf2e.spells-srd.Item.VlNcjmYyu95vOUe8"
        }
      },
      "img": "icons/magic/symbols/ring-circle-smoke-blue.webp",
      "name": "Dimension Door",
      "sort": 300000,
      "system": {
        "description": {
          "gm": "",
          "value": "<p>Opening a door that bypasses normal space, you instantly transport yourself and any items you're wearing and holding from your current space to a clear space within range you can see. If this would bring another creature with you-even if you're carrying it in an extradimensional container-the spell is lost.</p>\n<hr />\n<p><strong>Heightened (5th)</strong> The range increases to 1 mile. You don't need to be able to see your destination, as long as you have been there in the past and know its relative location and distance from you. You are temporarily immune for 1 hour.</p>"
        },
        "rules": [],
        "slug": "dimension-door",
        "_migration": {
          "version": 0.935,
          "lastMigration": null,
          "previous": {
            "schema": 0.932,
            "foundry": "12.331",
            "system": "6.7.2"
          }
        },
        "traits": {
          "otherTags": [],
          "value": [
            "concentrate",
            "manipulate",
            "teleportation"
          ],
          "rarity": "common",
          "traditions": [
            "arcane",
            "occult"
          ]
        },
        "publication": {
          "title": "Pathfinder Core Rulebook",
          "authors": "",
          "license": "OGL",
          "remaster": false
        },
        "level": {
          "value": 4
        },
        "requirements": "",
        "target": {
          "value": ""
        },
        "range": {
          "value": "120 feet"
        },
        "area": null,
        "time": {
          "value": "2"
        },
        "duration": {
          "value": "",
          "sustained": false
        },
        "damage": {},
        "defense": null,
        "cost": {
          "value": ""
        },
        "location": {
          "value": "QnuvWppYTYaOJTUu",
          "heightenedLevel": 4,
          "uses": {
            "max": 3,
            "value": 3
          }
        },
        "counteraction": false,
        "heightening": {
          "levels": {
            "5": {
              "range": {
                "value": "1 mile"
              }
            }
          },
          "type": "fixed"
        }
      },
      "type": "spell",
      "_stats": {
        "compendiumSource": "Compendium.pf2e.spells-srd.Item.VlNcjmYyu95vOUe8",
        "duplicateSource": null,
        "coreVersion": "12.331",
        "systemId": "pf2e",
        "systemVersion": "6.7.2"
      },
      "effects": [],
      "folder": null,
      "ownership": {
        "default": 0
      },
      "_key": "!actors.items!iII08V0HlvWGWSmu.pADzomLeub6qyUdT"
    },
    {
      "_id": "YRLPdASKAl0Y17jC",
      "flags": {
        "core": {
          "sourceId": "Compendium.pf2e.spells-srd.Item.yhz9fF69uwRhnHix"
        }
      },
      "img": "icons/creatures/birds/raptor-owl-flying-moon.webp",
      "name": "Animal Messenger",
      "sort": 400000,
      "system": {
        "description": {
          "gm": "",
          "value": "<p>You offer food, and an ordinary Tiny animal within range approaches to eat it. You imprint the image, direction, and distance of an obvious place or landmark well known to you within the animal. You can also attach a small object or note up to light Bulk to it. The animal does its best to reach the destination; if it makes it there, it waits nearby and allows nonhostile creatures to approach and remove the attached object. The spell ends after the message is delivered or after 24 hours, whichever comes first.</p>\n<p>If there are no Tiny wild animals in range, the spell is lost.</p>"
        },
        "rules": [],
        "slug": "animal-messenger",
        "_migration": {
          "version": 0.935,
          "lastMigration": null,
          "previous": {
            "schema": 0.932,
            "foundry": "12.331",
            "system": "6.7.2"
          }
        },
        "traits": {
          "otherTags": [],
          "value": [
            "concentrate",
            "manipulate",
            "mental"
          ],
          "rarity": "common",
          "traditions": [
            "primal"
          ]
        },
        "publication": {
          "title": "Pathfinder Core Rulebook",
          "authors": "",
          "license": "OGL",
          "remaster": false
        },
        "level": {
          "value": 2
        },
        "requirements": "",
        "target": {
          "value": ""
        },
        "range": {
          "value": "120 feet"
        },
        "area": null,
        "time": {
          "value": "1 minute"
        },
        "duration": {
          "value": "see text",
          "sustained": false
        },
        "damage": {},
        "defense": null,
        "cost": {
          "value": ""
        },
        "location": {
          "value": "QnuvWppYTYaOJTUu",
          "heightenedLevel": 2,
          "uses": {
            "max": 3,
            "value": 3
          }
        },
        "counteraction": false
      },
      "type": "spell",
      "_stats": {
        "compendiumSource": "Compendium.pf2e.spells-srd.Item.yhz9fF69uwRhnHix",
        "duplicateSource": null,
        "coreVersion": "12.331",
        "systemId": "pf2e",
        "systemVersion": "6.7.2"
      },
      "effects": [],
      "folder": null,
      "ownership": {
        "default": 0
      },
      "_key": "!actors.items!iII08V0HlvWGWSmu.YRLPdASKAl0Y17jC"
    },
    {
      "_id": "RM1LE1Hf6klj9jeF",
      "flags": {
        "core": {
          "sourceId": "Compendium.pf2e.spells-srd.Item.vLA0q0WOK2YPuJs6"
        }
      },
      "img": "systems/pf2e/icons/spells/charm.webp",
      "name": "Charm (Animals Only)",
      "sort": 500000,
      "system": {
        "description": {
          "gm": "",
          "value": "<p>To the target, your words are honey and your visage seems bathed in a dreamy haze. It must attempt a Will save, with a +4 circumstance bonus if you or your allies recently threatened it or used hostile actions against it.</p>\n<p>You can Dismiss the spell. If you use hostile actions against the target, the spell ends. When the spell ends, the target doesn't necessarily realize it was charmed unless its friendship with you or the actions you convinced it to take clash with its expectations, meaning you could potentially convince the target to continue being your friend via mundane means.</p>\n<hr />\n<p><strong>Critical Success</strong> The target is unaffected and aware you tried to charm it.</p>\n<p><strong>Success</strong> The target is unaffected but thinks your spell was something harmless instead of charm, unless it identifies the spell.</p>\n<p><strong>Failure</strong> The target's attitude becomes @UUID[Compendium.pf2e.conditionitems.Item.v66R7FdOf11l94im]{Friendly} toward you. If it was Friendly, it becomes @UUID[Compendium.pf2e.conditionitems.Item.v44P3WUcU1j0115l]{Helpful}. It can't use hostile actions against you.</p>\n<p><strong>Critical Failure</strong> The target's attitude becomes Helpful toward you, and it can't use hostile actions against you.</p>\n<hr />\n<p><strong>Heightened (4th)</strong> The duration lasts until the next time you make your daily preparations.</p>\n<p><strong>Heightened (8th)</strong> The duration lasts until the next time you make your daily preparations, and you can target up to 10 creatures.</p>"
        },
        "rules": [],
        "slug": "charm",
        "_migration": {
          "version": 0.935,
          "lastMigration": null,
          "previous": {
            "schema": 0.932,
            "foundry": "12.331",
            "system": "6.7.2"
          }
        },
        "traits": {
          "otherTags": [],
          "value": [
            "concentrate",
            "emotion",
            "incapacitation",
            "manipulate",
            "mental"
          ],
          "rarity": "common",
          "traditions": [
            "arcane",
            "occult",
            "primal"
          ]
        },
        "publication": {
          "title": "Pathfinder Core Rulebook",
          "authors": "",
          "license": "OGL",
          "remaster": false
        },
        "level": {
          "value": 1
        },
        "requirements": "",
        "target": {
          "value": "1 creature"
        },
        "range": {
          "value": "30 feet"
        },
        "area": null,
        "time": {
          "value": "2"
        },
        "duration": {
          "value": "1 hour",
          "sustained": false
        },
        "damage": {},
        "defense": {
          "save": {
            "basic": false,
            "statistic": "will"
          }
        },
        "cost": {
          "value": ""
        },
        "location": {
          "value": "QnuvWppYTYaOJTUu",
          "heightenedLevel": 1,
          "uses": {
            "max": 3,
            "value": 3
          }
        },
        "counteraction": false,
        "heightening": {
          "levels": {
            "8": {
              "target": {
                "value": "10 creatures"
              }
            }
          },
          "type": "fixed"
        }
      },
      "type": "spell",
      "_stats": {
        "compendiumSource": "Compendium.pf2e.spells-srd.Item.vLA0q0WOK2YPuJs6",
        "duplicateSource": null,
        "coreVersion": "12.331",
        "systemId": "pf2e",
        "systemVersion": "6.7.2"
      },
      "effects": [],
      "folder": null,
      "ownership": {
        "default": 0
      },
      "_key": "!actors.items!iII08V0HlvWGWSmu.RM1LE1Hf6klj9jeF"
    },
    {
      "_id": "zFX3wGhum9cawq1L",
      "flags": {
        "core": {
          "sourceId": "Compendium.pf2e.spells-srd.Item.kl2q6JvBZwed4B6v"
        }
      },
      "img": "systems/pf2e/icons/spells/dancing-lights.webp",
      "name": "Dancing Lights",
      "sort": 600000,
      "system": {
        "description": {
          "gm": "",
          "value": "<p>You create up to four floating lights, no two of which are more than 10 feet apart. Each sheds light like a torch. When you Sustain the Spell, you can move any number of lights up to 60 feet. Each light must remain within 120 feet of you and within 10 feet of all others, or it winks out.</p>"
        },
        "rules": [],
        "slug": "dancing-lights",
        "_migration": {
          "version": 0.935,
          "lastMigration": null,
          "previous": {
            "schema": 0.932,
            "foundry": "12.331",
            "system": "6.7.2"
          }
        },
        "traits": {
          "otherTags": [],
          "value": [
            "cantrip",
            "concentrate",
            "light",
            "manipulate"
          ],
          "rarity": "common",
          "traditions": [
            "arcane",
            "occult",
            "primal"
          ]
        },
        "publication": {
          "title": "Pathfinder Core Rulebook",
          "authors": "",
          "license": "OGL",
          "remaster": false
        },
        "level": {
          "value": 1
        },
        "requirements": "",
        "target": {
          "value": ""
        },
        "range": {
          "value": "120 feet"
        },
        "area": null,
        "time": {
          "value": "2"
        },
        "duration": {
          "value": "",
          "sustained": true
        },
        "damage": {},
        "defense": null,
        "cost": {
          "value": ""
        },
        "location": {
          "value": "QnuvWppYTYaOJTUu"
        },
        "counteraction": false
      },
      "type": "spell",
      "_stats": {
        "compendiumSource": "Compendium.pf2e.spells-srd.Item.kl2q6JvBZwed4B6v",
        "duplicateSource": null,
        "coreVersion": "12.331",
        "systemId": "pf2e",
        "systemVersion": "6.7.2"
      },
      "effects": [],
      "folder": null,
      "ownership": {
        "default": 0
      },
      "_key": "!actors.items!iII08V0HlvWGWSmu.zFX3wGhum9cawq1L"
    },
    {
      "_id": "ihhInjmGQpLuKLup",
      "flags": {
        "core": {
          "sourceId": "Compendium.pf2e.spells-srd.Item.Gb7SeieEvd0pL2Eh"
        }
      },
      "img": "icons/skills/melee/strike-blade-scimitar-gray-red.webp",
      "name": "True Strike",
      "sort": 700000,
      "system": {
        "description": {
          "gm": "",
          "value": "<p>A glimpse into the future ensures your next blow strikes true. The next time you make an attack roll before the end of your turn, roll the attack twice and use the better result. The attack ignores circumstance penalties to the attack roll and any flat check required due to the target being @UUID[Compendium.pf2e.conditionitems.Item.DmAIPqOBomZ7H95W]{Concealed} or @UUID[Compendium.pf2e.conditionitems.Item.iU0fEDdBp3rXpTMC]{Hidden}.</p>\n<p>@UUID[Compendium.pf2e.spell-effects.Item.fpGDAz2v5PG0zUSl]{Spell Effect: Sure Strike}</p>"
        },
        "rules": [],
        "slug": "true-strike",
        "_migration": {
          "version": 0.935,
          "lastMigration": null,
          "previous": {
            "schema": 0.932,
            "foundry": "12.331",
            "system": "6.7.2"
          }
        },
        "traits": {
          "otherTags": [],
          "value": [
            "concentrate",
            "fortune"
          ],
          "rarity": "common",
          "traditions": [
            "arcane",
            "occult"
          ]
        },
        "publication": {
          "title": "Pathfinder Core Rulebook",
          "authors": "",
          "license": "OGL",
          "remaster": false
        },
        "level": {
          "value": 1
        },
        "requirements": "",
        "target": {
          "value": ""
        },
        "range": {
          "value": ""
        },
        "area": null,
        "time": {
          "value": "1"
        },
        "duration": {
          "value": "until the end of your turn",
          "sustained": false
        },
        "damage": {},
        "defense": null,
        "cost": {
          "value": ""
        },
        "location": {
          "value": "QnuvWppYTYaOJTUu",
          "heightenedLevel": 1,
          "uses": {
            "max": 3,
            "value": 3
          }
        },
        "counteraction": false
      },
      "type": "spell",
      "_stats": {
        "compendiumSource": "Compendium.pf2e.spells-srd.Item.Gb7SeieEvd0pL2Eh",
        "duplicateSource": null,
        "coreVersion": "12.331",
        "systemId": "pf2e",
        "systemVersion": "6.7.2"
      },
      "effects": [],
      "folder": null,
      "ownership": {
        "default": 0
      },
      "_key": "!actors.items!iII08V0HlvWGWSmu.ihhInjmGQpLuKLup"
    },
    {
      "_id": "z4Cumz0pj2Sd3qCZ",
      "flags": {
        "core": {
          "sourceId": "Compendium.pf2e.equipment-srd.Item.dUC8Fsa6FZtVikS3"
        }
      },
      "img": "systems/pf2e/icons/equipment/weapons/composite-longbow.webp",
      "name": "Composite Longbow",
      "sort": 800000,
      "system": {
        "description": {
          "gm": "",
          "value": "<p>This projectile weapon is made from horn, wood, and sinew laminated together to increase the power of its pull and the force of its projectile. Like all longbows, its great size also increases the bow's range and power. You must use two hands to fire it, and it cannot be used while mounted. Any time an ability is specifically restricted to a longbow, such as Erastil's favored weapon, it also applies to composite longbows unless otherwise stated.</p>"
        },
        "rules": [],
        "slug": "composite-longbow",
        "_migration": {
          "version": 0.935,
          "lastMigration": null,
          "previous": {
            "schema": 0.932,
            "foundry": "12.331",
            "system": "6.7.2"
          }
        },
        "traits": {
          "otherTags": [],
          "value": [
            "deadly-d10",
            "propulsive",
            "volley-30"
          ],
          "rarity": "common"
        },
        "publication": {
          "title": "",
          "authors": "",
          "license": "OGL",
          "remaster": false
        },
        "level": {
          "value": 0
        },
        "quantity": 1,
        "baseItem": "composite-longbow",
        "bulk": {
          "value": 2
        },
        "hp": {
          "value": 0,
          "max": 0
        },
        "hardness": 0,
        "price": {
          "value": {
            "gp": 20
          }
        },
        "equipped": {
          "carryType": "held",
          "invested": null,
          "handsHeld": 1
        },
        "containerId": null,
        "size": "med",
        "material": {
          "type": null,
          "grade": null
        },
        "identification": {
          "status": "identified",
          "unidentified": {
            "name": "",
            "img": "",
            "data": {
              "description": {
                "value": ""
              }
            }
          },
          "misidentified": {}
        },
        "usage": {
          "value": "held-in-one-plus-hands"
        },
        "category": "martial",
        "group": "bow",
        "bonus": {
          "value": 0
        },
        "damage": {
          "dice": 1,
          "die": "d8",
          "damageType": "piercing",
          "persistent": null
        },
        "bonusDamage": {
          "value": 0
        },
        "splashDamage": {
          "value": 0
        },
        "range": 100,
        "reload": {
          "value": "0"
        },
        "runes": {
          "potency": 0,
          "striking": 0,
          "property": []
        },
        "specific": null,
        "subitems": [],
        "property1": {
          "value": "",
          "dice": 0,
          "die": "",
          "damageType": "",
          "critDice": 0,
          "critDie": "",
          "critDamage": "",
          "critDamageType": ""
        }
      },
      "type": "weapon",
      "_stats": {
        "compendiumSource": "Compendium.pf2e.equipment-srd.Item.dUC8Fsa6FZtVikS3",
        "duplicateSource": null,
        "coreVersion": "12.331",
        "systemId": "pf2e",
        "systemVersion": "6.7.2"
      },
      "effects": [],
      "folder": null,
      "ownership": {
        "default": 0
      },
      "_key": "!actors.items!iII08V0HlvWGWSmu.z4Cumz0pj2Sd3qCZ"
    },
    {
      "_id": "PdU6HDBEmxAO2M84",
      "flags": {
        "core": {
          "sourceId": "Compendium.pf2e.equipment-srd.Item.w2ENw2VMPcsbif8g"
        }
      },
      "img": "systems/pf2e/icons/equipment/weapons/arrows.webp",
      "name": "Arrows",
      "sort": 900000,
      "system": {
        "description": {
          "gm": "",
          "value": "<p>These projectiles are the ammunition for bows. The shaft of an arrow is made of wood. It is stabilized in flight by fletching at one end and bears a metal head on the other.</p>"
        },
        "rules": [],
        "slug": "arrows",
        "_migration": {
          "version": 0.935,
          "lastMigration": null,
          "previous": {
            "schema": 0.932,
            "foundry": "12.331",
            "system": "6.7.2"
          }
        },
        "traits": {
          "otherTags": [],
          "value": [],
          "rarity": "common"
        },
        "publication": {
          "title": "",
          "authors": "",
          "license": "OGL",
          "remaster": false
        },
        "level": {
          "value": 0
        },
        "quantity": 20,
        "baseItem": null,
        "bulk": {
          "value": 0.1
        },
        "hp": {
          "value": 0,
          "max": 0
        },
        "hardness": 0,
        "price": {
          "value": {
            "sp": 1
          },
          "per": 10
        },
        "equipped": {
          "carryType": "held",
          "handsHeld": 1
        },
        "containerId": null,
        "size": "med",
        "material": {
          "type": null,
          "grade": null
        },
        "identification": {
          "status": "identified",
          "unidentified": {
            "name": "",
            "img": "",
            "data": {
              "description": {
                "value": ""
              }
            }
          },
          "misidentified": {}
        },
        "category": "ammo",
        "uses": {
          "value": 1,
          "max": 1,
          "autoDestroy": true
        },
        "damage": null,
        "usage": {
          "value": "held-in-one-hand"
        },
        "stackGroup": "arrows",
        "spell": null
      },
      "type": "consumable",
      "_stats": {
        "compendiumSource": "Compendium.pf2e.equipment-srd.Item.w2ENw2VMPcsbif8g",
        "duplicateSource": null,
        "coreVersion": "12.331",
        "systemId": "pf2e",
        "systemVersion": "6.7.2"
      },
      "effects": [],
      "folder": null,
      "ownership": {
        "default": 0
      },
      "_key": "!actors.items!iII08V0HlvWGWSmu.PdU6HDBEmxAO2M84"
    },
    {
      "_id": "qJWbB2v6gs9de4fv",
      "img": "systems/pf2e/icons/default-icons/melee.svg",
      "name": "Horn",
      "sort": 1000000,
      "system": {
        "attackEffects": {
          "value": [
            "push"
          ]
        },
        "bonus": {
          "value": 11
        },
        "damageRolls": {
          "cdztrz6c3olg30xghi9m": {
            "damage": "2d8+3",
            "damageType": "piercing",
            "category": null
          },
          "mpv0rmpm4bjo561x4l7v": {
            "damage": "1d6",
            "damageType": "spirit",
            "category": null
          }
        },
        "description": {
          "value": "",
          "gm": ""
        },
        "publication": {
          "license": "OGL",
          "remaster": false,
          "title": "",
          "authors": ""
        },
        "rules": [],
        "slug": null,
        "traits": {
          "value": [
            "holy",
            "magical"
          ],
          "otherTags": []
        },
        "_migration": {
          "version": 0.935,
          "previous": {
            "schema": 0.932,
            "foundry": "12.331",
            "system": "6.7.2"
          }
        }
      },
      "type": "melee",
      "_stats": {
        "compendiumSource": null,
        "duplicateSource": null,
        "coreVersion": "12.331",
        "systemId": "pf2e",
        "systemVersion": "6.7.2"
      },
      "effects": [],
      "folder": null,
      "ownership": {
        "default": 0
      },
      "flags": {},
      "_key": "!actors.items!iII08V0HlvWGWSmu.qJWbB2v6gs9de4fv"
    },
    {
      "_id": "qniHJ3WvDHkUKTJ3",
      "flags": {
        "pf2e": {
          "linkedWeapon": "z4Cumz0pj2Sd3qCZ"
        }
      },
      "img": "systems/pf2e/icons/default-icons/melee.svg",
      "name": "Composite Longbow",
      "sort": 1100000,
      "system": {
        "attackEffects": {
          "value": []
        },
        "bonus": {
          "value": 14
        },
        "damageRolls": {
          "71i98k84buqm3mcgzi8k": {
            "damage": "1d8+4",
            "damageType": "piercing",
            "category": null
          },
          "sq8w2dbxizgmsybefcpk": {
            "damage": "1d6",
            "damageType": "spirit",
            "category": null
          }
        },
        "description": {
          "value": "",
          "gm": ""
        },
        "publication": {
          "license": "OGL",
          "remaster": false,
          "title": "",
          "authors": ""
        },
        "rules": [],
        "slug": null,
        "traits": {
          "value": [
            "deadly-d10",
            "holy",
            "magical",
            "range-increment-100",
            "reload-0",
            "volley-30"
          ],
          "otherTags": []
        },
        "_migration": {
          "version": 0.935,
          "previous": {
            "schema": 0.932,
            "foundry": "12.331",
            "system": "6.7.2"
          }
        }
      },
      "type": "melee",
      "_stats": {
        "compendiumSource": null,
        "duplicateSource": null,
        "coreVersion": "12.331",
        "systemId": "pf2e",
        "systemVersion": "6.7.2"
      },
      "effects": [],
      "folder": null,
      "ownership": {
        "default": 0
      },
      "_key": "!actors.items!iII08V0HlvWGWSmu.qniHJ3WvDHkUKTJ3"
    },
    {
      "_id": "9B8Sr2aqKRJttXog",
      "flags": {
        "core": {
          "sourceId": "Compendium.pf2e.bestiary-ability-glossary-srd.Item.kakyXBG5WA8c6Zfd"
        }
      },
      "img": "systems/pf2e/icons/actions/Passive.webp",
      "name": "Constant Spells",
      "sort": 1200000,
      "system": {
        "description": {
          "gm": "",
          "value": "<p>@Localize[PF2E.NPC.Abilities.Glossary.ConstantSpells]</p>"
        },
        "rules": [],
        "slug": "constant-spells",
        "_migration": {
          "version": 0.935,
          "previous": {
            "schema": 0.932,
            "foundry": "12.331",
            "system": "6.7.2"
          }
        },
        "traits": {
          "otherTags": [],
          "value": []
        },
        "publication": {
          "title": "Pathfinder Bestiary",
          "authors": "",
          "license": "OGL",
          "remaster": false
        },
        "actionType": {
          "value": "passive"
        },
        "category": "interaction",
        "actions": {
          "value": null
        },
        "deathNote": false
      },
      "type": "action",
      "_stats": {
        "compendiumSource": "Compendium.pf2e.bestiary-ability-glossary-srd.Item.kakyXBG5WA8c6Zfd",
        "duplicateSource": null,
        "coreVersion": "12.331",
        "systemId": "pf2e",
        "systemVersion": "6.7.2"
      },
      "effects": [],
      "folder": null,
      "ownership": {
        "default": 0
      },
      "_key": "!actors.items!iII08V0HlvWGWSmu.9B8Sr2aqKRJttXog"
    },
    {
      "_id": "8KbESiYnn2ngs6MZ",
      "flags": {
        "core": {
          "sourceId": "Compendium.pf2e.bestiary-ability-glossary-srd.Item.kquBnQ0kObZztnBc"
        }
      },
      "img": "systems/pf2e/icons/actions/Passive.webp",
      "name": "+1 Status to All Saves vs. Magic",
      "sort": 1300000,
      "system": {
        "description": {
          "gm": "",
          "value": ""
        },
        "rules": [
          {
            "key": "FlatModifier",
            "predicate": [
              {
                "or": [
                  "magical",
                  "arcane",
                  "divine",
                  "primal",
                  "occult"
                ]
              }
            ],
            "selector": "saving-throw",
            "type": "status",
            "value": 1
          }
        ],
        "slug": "1-status-to-all-saves-vs-magic",
        "_migration": {
          "version": 0.935,
          "previous": {
            "schema": 0.932,
            "foundry": "12.331",
            "system": "6.7.2"
          }
        },
        "traits": {
          "otherTags": [],
          "value": []
        },
        "publication": {
          "title": "",
          "authors": "",
          "license": "OGL",
          "remaster": false
        },
        "actionType": {
          "value": "passive"
        },
        "category": "defensive",
        "actions": {
          "value": null
        },
        "deathNote": false
      },
      "type": "action",
      "_stats": {
        "compendiumSource": "Compendium.pf2e.bestiary-ability-glossary-srd.Item.kquBnQ0kObZztnBc",
        "duplicateSource": null,
        "coreVersion": "12.331",
        "systemId": "pf2e",
        "systemVersion": "6.7.2"
      },
      "effects": [],
      "folder": null,
      "ownership": {
        "default": 0
      },
      "_key": "!actors.items!iII08V0HlvWGWSmu.8KbESiYnn2ngs6MZ"
    },
    {
      "_id": "IqlIzn7bY9FduX6g",
      "img": "systems/pf2e/icons/actions/Passive.webp",
      "name": "Menacing Guardian",
      "sort": 1400000,
      "system": {
        "description": {
          "gm": "",
          "value": "<p>30 feet. Enemies that start their turn in the area or enter it must attempt a @Check[type:will|dc:19] save.</p>\n<p>On a failure, they take a -1 status penalty to attack rolls, spell rolls, and damage rolls against any other target while in the aura for 24 hours or until they damage the archon, whichever comes first. On a critical failure, they can't use hostile actions against any other target while in the area for 24 hours or until they damage the archon, whichever comes first.</p>\n<p>Regardless of the result, a creature is then temporarily immune to further menacing guardian auras for 24 hours.</p>"
        },
        "rules": [
          {
            "key": "Aura",
            "radius": 30,
            "slug": "menacing-guardian",
            "traits": [
              "divine"
            ]
          }
        ],
        "slug": null,
        "_migration": {
          "version": 0.935,
          "previous": {
            "schema": 0.932,
            "foundry": "12.331",
            "system": "6.7.2"
          }
        },
        "traits": {
          "otherTags": [],
          "value": [
            "aura",
            "divine"
          ]
        },
        "publication": {
          "title": "",
          "authors": "",
          "license": "OGL",
          "remaster": false
        },
        "actionType": {
          "value": "passive"
        },
        "category": "defensive",
        "actions": {
          "value": null
        },
        "deathNote": false
      },
      "type": "action",
      "_stats": {
        "compendiumSource": null,
        "duplicateSource": null,
        "coreVersion": "12.331",
        "systemId": "pf2e",
        "systemVersion": "6.7.2"
      },
      "effects": [],
      "folder": null,
      "ownership": {
        "default": 0
      },
      "flags": {},
      "_key": "!actors.items!iII08V0HlvWGWSmu.IqlIzn7bY9FduX6g"
    },
    {
      "_id": "9FQ3eh9wkGZD4b1O",
      "img": "systems/pf2e/icons/actions/Reaction.webp",
      "name": "Retributive Strike",
      "sort": 1500000,
      "system": {
        "description": {
          "gm": "",
          "value": "<p><strong>Damage Reduction</strong> 6</p>\n<p>A horned archon can also make a Retributive Strike with its composite longbow</p>\n<hr />\n<p>@Localize[PF2E.NPC.Abilities.Glossary.RetributiveStrike]</p>"
        },
        "rules": [],
        "slug": "retributive-strike",
        "_migration": {
          "version": 0.935,
          "previous": {
            "schema": 0.932,
            "foundry": "12.331",
            "system": "6.7.2"
          }
        },
        "traits": {
          "otherTags": [],
          "value": []
        },
        "publication": {
          "title": "",
          "authors": "",
          "license": "OGL",
          "remaster": false
        },
        "actionType": {
          "value": "reaction"
        },
        "category": "defensive",
        "actions": {
          "value": null
        },
        "deathNote": false
      },
      "type": "action",
      "_stats": {
        "compendiumSource": null,
        "duplicateSource": null,
        "coreVersion": "12.331",
        "systemId": "pf2e",
        "systemVersion": "6.7.2"
      },
      "effects": [],
      "folder": null,
      "ownership": {
        "default": 0
      },
      "flags": {},
      "_key": "!actors.items!iII08V0HlvWGWSmu.9FQ3eh9wkGZD4b1O"
    },
    {
      "_id": "5xEEdMhQDZQFuUpv",
      "img": "systems/pf2e/icons/actions/Passive.webp",
      "name": "Archon's Door",
      "sort": 1600000,
      "system": {
        "description": {
          "gm": "",
          "value": "<p>Once per day, if an archon sees another creature cast @UUID[Compendium.pf2e.spells-srd.Item.VlNcjmYyu95vOUe8]{Translocate}, it can cast an innate <em>dimension door</em> (heightened to 5th level) within 1 round to attempt to follow that creature to the maximum distance of the archon's <em>dimension door</em>.</p>\n<p>If the archon's <em>dimension door</em> has enough distance, the archon appears the same distance and direction from the creature as before either used <em>dimension door</em>.</p>"
        },
        "rules": [],
        "slug": null,
        "_migration": {
          "version": 0.935,
          "previous": {
            "schema": 0.932,
            "foundry": "12.331",
            "system": "6.7.2"
          }
        },
        "traits": {
          "otherTags": [],
          "value": []
        },
        "publication": {
          "title": "",
          "authors": "",
          "license": "OGL",
          "remaster": false
        },
        "actionType": {
          "value": "passive"
        },
        "category": "offensive",
        "actions": {
          "value": null
        },
        "deathNote": false
      },
      "type": "action",
      "_stats": {
        "compendiumSource": null,
        "duplicateSource": null,
        "coreVersion": "12.331",
        "systemId": "pf2e",
        "systemVersion": "6.7.2"
      },
      "effects": [],
      "folder": null,
      "ownership": {
        "default": 0
      },
      "flags": {},
      "_key": "!actors.items!iII08V0HlvWGWSmu.5xEEdMhQDZQFuUpv"
    },
    {
      "_id": "cPuEYKhbrReSjt1J",
      "img": "systems/pf2e/icons/actions/OneAction.webp",
      "name": "Touch of Charity",
      "sort": 1700000,
      "system": {
        "description": {
          "gm": "",
          "value": "<p>A horned archon can touch another creature to take on that creature's wounds, transferring up to 30 of the horned archon's HP to the touched creature. The horned archon can't transfer more HP than it currently has.</p>"
        },
        "rules": [],
        "slug": null,
        "_migration": {
          "version": 0.935,
          "previous": {
            "schema": 0.932,
            "foundry": "12.331",
            "system": "6.7.2"
          }
        },
        "traits": {
          "otherTags": [],
          "value": [
            "healing",
            "manipulate"
          ]
        },
        "publication": {
          "title": "",
          "authors": "",
          "license": "OGL",
          "remaster": false
        },
        "actionType": {
          "value": "action"
        },
        "category": "offensive",
        "actions": {
          "value": 1
        },
        "deathNote": false
      },
      "type": "action",
      "_stats": {
        "compendiumSource": null,
        "duplicateSource": null,
        "coreVersion": "12.331",
        "systemId": "pf2e",
        "systemVersion": "6.7.2"
      },
      "effects": [],
      "folder": null,
      "ownership": {
        "default": 0
      },
      "flags": {},
      "_key": "!actors.items!iII08V0HlvWGWSmu.cPuEYKhbrReSjt1J"
    },
    {
      "_id": "g832bFUMFhXs1T6E",
      "flags": {
        "core": {
          "sourceId": "Compendium.pf2e.bestiary-ability-glossary-srd.Item.t6cx9FOODmeZQNYl"
        }
      },
      "img": "systems/pf2e/icons/actions/OneAction.webp",
      "name": "Push",
      "sort": 1800000,
      "system": {
        "description": {
          "gm": "",
          "value": "<p>@Localize[PF2E.NPC.Abilities.Glossary.Push]</p>"
        },
        "rules": [],
        "slug": "push",
        "_migration": {
          "version": 0.935,
          "previous": {
            "schema": 0.932,
            "foundry": "12.331",
            "system": "6.7.2"
          }
        },
        "traits": {
          "otherTags": [],
          "value": []
        },
        "publication": {
          "title": "Pathfinder Bestiary",
          "authors": "",
          "license": "OGL",
          "remaster": false
        },
        "actionType": {
          "value": "action"
        },
        "category": "offensive",
        "actions": {
          "value": 1
        },
        "deathNote": false
      },
      "type": "action",
      "_stats": {
        "compendiumSource": "Compendium.pf2e.bestiary-ability-glossary-srd.Item.t6cx9FOODmeZQNYl",
        "duplicateSource": null,
        "coreVersion": "12.331",
        "systemId": "pf2e",
        "systemVersion": "6.7.2"
      },
      "effects": [],
      "folder": null,
      "ownership": {
        "default": 0
      },
      "_key": "!actors.items!iII08V0HlvWGWSmu.g832bFUMFhXs1T6E"
    }
  ],
  "name": "Horned Archon",
  "system": {
    "attributes": {
      "hp": {
        "value": 65,
        "temp": 0,
        "max": 65,
        "details": ""
      },
      "speed": {
        "value": 35,
        "otherSpeeds": [],
        "details": ""
      },
      "ac": {
        "value": 22,
        "details": ""
      },
      "allSaves": {
        "value": "+1 status to all saves vs. magic"
      },
      "weaknesses": [
        {
          "type": "unholy",
          "value": 5
        }
      ]
    },
    "initiative": {
      "statistic": "perception"
    },
    "details": {
      "languages": {
        "value": [
          "diabolic",
          "draconic",
          "empyrean"
        ],
        "details": "tongues"
      },
      "level": {
        "value": 4
      },
      "blurb": "",
      "publicNotes": "<p>Horned archons are secretive and tireless sentinels and scouts, patrolling the Outer Sphere's untamed wilds for evil to eliminate and keeping small communities safe from demons, devils, and worse. They resemble muscular humans with the head, horns, and legs of a stag. When requested to do so by their patrons, especially Erastil, they journey to the Material Plane and patrol dangerous frontier areas, secretly performing acts of kindness such as leading hunters to food, helping lost children, and driving off evil creatures. Because they roam the wilds of Nirvana and Elysium, horned archons are among the best at understanding the perspectives of other celestials.</p>\n<hr />\n<p>Archons are guardians of Heaven and enemies of chaos and evil. They openly fight back the spread of fiends but also quietly nurture the seeds of virtue within mortals, teaching the denizens of the Material Plane how to act with honor and integrity, enact just laws, and cast off sin and temptation.</p>\n<p>Archons live in the immense seven-tiered mountain of Heaven. They manifest in the Garden at the mountain's peak from mortal souls who answer a mysterious voice. There they swear to forever serve the cause of justice and transform into their new archon forms. Intensely orderly in their metamorphosis, new archons begin as lantern archons or other lesser forms, transforming into ever-greater archons as their virtue and achievements grow. Each archon represents a particular virtue, such as hope, charity, justice, or courage, and they gain strength in the presence of mortals who exemplify this virtue. Due to their extremely lawful nature, archons sometimes find themselves at odds with azatas.</p>",
      "privateNotes": "",
      "publication": {
        "title": "Pathfinder Bestiary",
        "authors": "",
        "license": "OGL",
        "remaster": false
      }
    },
    "resources": {
      "focus": {
        "max": 1,
        "value": 1
      }
    },
    "_migration": {
      "version": 0.935,
      "previous": {
        "schema": 0.932,
        "foundry": "12.331",
        "system": "6.7.2"
      }
    },
    "abilities": {
      "str": {
        "mod": 3
      },
      "dex": {
        "mod": 4
      },
      "con": {
        "mod": 3
      },
      "int": {
        "mod": 1
      },
      "wis": {
        "mod": 3
      },
      "cha": {
        "mod": 1
      }
    },
    "perception": {
      "details": "",
      "mod": 11,
      "senses": [
        {
          "type": "darkvision"
        }
      ],
      "vision": true
    },
    "saves": {
      "fortitude": {
        "value": 11,
        "saveDetail": ""
      },
      "reflex": {
        "value": 10,
        "saveDetail": ""
      },
      "will": {
        "value": 11,
        "saveDetail": ""
      }
    },
    "skills": {
      "acrobatics": {
        "base": 12
      },
      "nature": {
        "base": 11
      },
      "religion": {
        "base": 9
      },
      "stealth": {
        "base": 10
      },
      "survival": {
        "base": 11,
        "special": [
          {
            "base": 15,
            "label": "to Track",
            "predicate": [
              "action:track"
            ]
          }
        ]
      }
    },
    "traits": {
      "value": [
        "archon",
        "celestial",
        "good",
        "holy",
        "lawful"
      ],
      "rarity": "common",
      "size": {
        "value": "med"
      }
    }
  },
  "type": "npc",
  "_stats": {
    "compendiumSource": "Compendium.pf2e.pathfinder-bestiary.Actor.iII08V0HlvWGWSmu",
    "duplicateSource": null,
    "coreVersion": "12.331",
    "systemId": "pf2e",
    "systemVersion": "6.7.2"
  },
  "flags": {
    "core": {
      "sourceId": "Compendium.pf2e.pathfinder-bestiary.Actor.iII08V0HlvWGWSmu"
    }
  },
  "effects": [],
  "folder": "SVPGmKtBEGkOqZqL",
  "ownership": {
    "default": 0,
    "Yb7GAnhzVbd5I9T9": 3
  },
  "sort": 0,
  "_key": "!actors!iII08V0HlvWGWSmu"
}
