{
  "_id": "q5qmNn144ZJGxnvJ",
  "img": "systems/pf2e/icons/spells/befitting-attire.webp",
  "name": "Befitting Attire",
  "system": {
    "description": {
      "gm": "",
      "value": "<p>You cloak the targets in an illusion, shaping their clothing and worn items into ones suitable for a particular occasion. You visualize the occasion, and the spell creates illusory attire customized to each target. For instance, if you visualized a noble ball, armor would appear to be fine clothing. This doesn't change identifying details of the targets' appearances other than their clothes.</p>\n<p>Any creature that touches the attire, uses the Seek action to examine it, or otherwise interacts with it can attempt to disbelieve your illusion.</p>\n<hr />\n<p><strong>Heightened (4th)</strong> You can target up to 20 creatures.</p>\n<p><strong>Heightened (5th)</strong> You can target up to 100 creatures.</p>"
    },
    "rules": [],
    "slug": "befitting-attire",
    "_migration": {
      "version": 0.935,
      "lastMigration": null,
      "previous": {
        "schema": 0.879,
        "foundry": "12.331",
        "system": "6.7.2"
      }
    },
    "traits": {
      "otherTags": [],
      "value": [
        "concentrate",
        "illusion",
        "manipulate",
        "visual"
      ],
      "rarity": "common",
      "traditions": [
        "arcane",
        "occult"
      ]
    },
    "publication": {
      "title": "Pathfinder Secrets of Magic",
      "authors": "",
      "license": "OGL",
      "remaster": false
    },
    "level": {
      "value": 2
    },
    "requirements": "",
    "target": {
      "value": "5 willing creatures"
    },
    "range": {
      "value": "30 feet"
    },
    "area": null,
    "time": {
      "value": "2"
    },
    "duration": {
      "value": "1 hour",
      "sustained": false
    },
    "damage": {},
    "defense": null,
    "cost": {
      "value": ""
    },
    "location": {
      "value": null
    },
    "counteraction": false,
    "heightening": {
      "levels": {
        "4": {
          "target": {
            "value": "20 willing creatures"
          }
        },
        "5": {
          "target": {
            "value": "100 willing creatures"
          }
        }
      },
      "type": "fixed"
    }
  },
  "type": "spell",
  "flags": {
    "core": {
      "sourceId": "Compendium.pf2e.spells-srd.Item.q5qmNn144ZJGxnvJ"
    }
  },
  "effects": [],
  "_stats": {
    "coreVersion": "12.331",
    "systemId": "pf2e",
    "systemVersion": "6.7.2",
    "compendiumSource": "Compendium.pf2e-legacy-content.spells-legacy.Item.q5qmNn144ZJGxnvJ",
    "duplicateSource": null
  },
  "folder": null,
  "sort": 0,
  "ownership": {
    "default": 0
  },
  "_key": "!items!q5qmNn144ZJGxnvJ"
}
