{
  "_id": "8TQiFzGf4feoHeH0",
  "img": "systems/pf2e/icons/spells/chilling-spray.webp",
  "name": "Chilling Spray",
  "system": {
    "description": {
      "gm": "",
      "value": "<p>A cone of icy shards bursts from your spread hands and coats the target in a layer of frost. You deal 2d4 cold damage to creatures in the area; they must each attempt a Reflex save.</p>\n<hr />\n<p><strong>Critical Success</strong> The creature takes no damage.</p>\n<p><strong>Success</strong> The creature takes half damage.</p>\n<p><strong>Failure</strong> The creature takes full damage and takes a -5-foot status penalty to its Speeds for 2 rounds.</p>\n<p><strong>Critical Failure</strong> The creature takes double damage and takes a -10-foot status penalty to its Speeds for 2 rounds.</p>\n<hr />\n<p><strong>Heightened (+1)</strong> The damage increases by 2d4.</p>"
    },
    "rules": [],
    "slug": "chilling-spray",
    "_migration": {
      "version": 0.935,
      "lastMigration": null,
      "previous": {
        "schema": 0.879,
        "foundry": "12.331",
        "system": "6.7.2"
      }
    },
    "traits": {
      "otherTags": [],
      "value": [
        "cold",
        "concentrate",
        "manipulate"
      ],
      "rarity": "common",
      "traditions": [
        "arcane",
        "primal"
      ]
    },
    "publication": {
      "title": "Pathfinder Advanced Player's Guide",
      "authors": "",
      "license": "OGL",
      "remaster": false
    },
    "level": {
      "value": 1
    },
    "requirements": "",
    "target": {
      "value": ""
    },
    "range": {
      "value": ""
    },
    "area": {
      "type": "cone",
      "value": 15
    },
    "time": {
      "value": "2"
    },
    "duration": {
      "value": "",
      "sustained": false
    },
    "damage": {
      "0": {
        "formula": "2d4",
        "type": "cold",
        "category": null,
        "materials": [],
        "kinds": [
          "damage"
        ]
      }
    },
    "defense": {
      "passive": null,
      "save": {
        "statistic": "reflex",
        "basic": false
      }
    },
    "cost": {
      "value": ""
    },
    "location": {
      "value": null
    },
    "counteraction": false,
    "heightening": {
      "damage": {
        "0": "2d4"
      },
      "interval": 1,
      "type": "interval"
    }
  },
  "type": "spell",
  "flags": {
    "core": {
      "sourceId": "Compendium.pf2e.spells-srd.Item.8TQiFzGf4feoHeH0"
    }
  },
  "effects": [],
  "_stats": {
    "coreVersion": "12.331",
    "systemId": "pf2e",
    "systemVersion": "6.7.2",
    "compendiumSource": "Compendium.pf2e-legacy-content.spells-legacy.Item.8TQiFzGf4feoHeH0",
    "duplicateSource": null
  },
  "folder": null,
  "sort": 0,
  "ownership": {
    "default": 0
  },
  "_key": "!items!8TQiFzGf4feoHeH0"
}
