{
  "_id": "lmHmKGs1N3yNAvln",
  "img": "systems/pf2e/icons/spells/wash-your-luck.webp",
  "name": "Wash Your Luck",
  "system": {
    "description": {
      "gm": "",
      "value": "<p>Some practitioners argue this spell literally washes your fortunes of all influences, malign or benign, while others claim it simply cleanses your mind of obsessions about luck and destiny. You adjust your garments, change the posture of your chair, fidget with a religious symbol, or make some other innocuous and personally significant action to wash away bad luck.</p>\n<p>Once during the spell's duration, before rolling a check, you can cancel out a misfortune effect on that roll, as normal when a fortune and misfortune effect apply to the same roll. After canceling out the misfortune effect, the spell ends, and you are then temporarily immune to wash your luck for 10 minutes.</p>\n<p>@UUID[Compendium.pf2e.spell-effects.Item.npFFTAxN44WWrGnM]{Spell Effect: Wash Your Luck}</p>"
    },
    "rules": [],
    "slug": "wash-your-luck",
    "_migration": {
      "version": 0.935,
      "lastMigration": null,
      "previous": {
        "schema": 0.879,
        "foundry": "12.331",
        "system": "6.7.2"
      }
    },
    "traits": {
      "otherTags": [],
      "value": [
        "cantrip",
        "concentrate",
        "fortune",
        "manipulate"
      ],
      "rarity": "common",
      "traditions": [
        "divine",
        "occult"
      ]
    },
    "publication": {
      "title": "Pathfinder Secrets of Magic",
      "authors": "",
      "license": "OGL",
      "remaster": false
    },
    "level": {
      "value": 1
    },
    "requirements": "",
    "target": {
      "value": ""
    },
    "range": {
      "value": ""
    },
    "area": null,
    "time": {
      "value": "2"
    },
    "duration": {
      "value": "1 minute",
      "sustained": false
    },
    "damage": {},
    "defense": null,
    "cost": {
      "value": ""
    },
    "location": {
      "value": null
    },
    "counteraction": false
  },
  "type": "spell",
  "flags": {
    "core": {
      "sourceId": "Compendium.pf2e.spells-srd.Item.lmHmKGs1N3yNAvln"
    }
  },
  "effects": [],
  "_stats": {
    "coreVersion": "12.331",
    "systemId": "pf2e",
    "systemVersion": "6.7.2",
    "compendiumSource": "Compendium.pf2e-legacy-content.spells-legacy.Item.lmHmKGs1N3yNAvln",
    "duplicateSource": null
  },
  "folder": null,
  "sort": 0,
  "ownership": {
    "default": 0
  },
  "_key": "!items!lmHmKGs1N3yNAvln"
}
