{
  "_id": "NZgjqVV2HYzLCvvA",
  "img": "systems/pf2e/icons/features/feats/feats.webp",
  "name": "Aldori Parry",
  "system": {
    "description": {
      "gm": "",
      "value": "<p><strong>Requirements</strong> You are wielding only an Aldori dueling sword and have your other hand or hands free.</p>\n<hr />\n<p>You can parry attacks against you with your Aldori dueling sword. You gain a +2 circumstance bonus to AC until the start of your next turn as long as you continue to meet the requirement.</p>\n<p>@UUID[Compendium.pf2e.feat-effects.Item.aEuDaQY1GnrrnDRA]{Effect: Aldori Parry}</p>"
    },
    "rules": [],
    "slug": "aldori-parry",
    "_migration": {
      "version": 0.935,
      "lastMigration": null,
      "previous": {
        "schema": 0.879,
        "foundry": "12.331",
        "system": "6.7.2"
      }
    },
    "traits": {
      "otherTags": [],
      "value": [
        "archetype"
      ],
      "rarity": "common"
    },
    "publication": {
      "title": "Pathfinder Lost Omens: World Guide",
      "authors": "",
      "license": "OGL",
      "remaster": false
    },
    "level": {
      "value": 4
    },
    "category": "class",
    "onlyLevel1": false,
    "maxTakable": 1,
    "actionType": {
      "value": "action"
    },
    "actions": {
      "value": 1
    },
    "prerequisites": {
      "value": [
        {
          "value": "Aldori Duelist Dedication"
        }
      ]
    },
    "location": null
  },
  "type": "feat",
  "flags": {
    "core": {
      "sourceId": "Compendium.pf2e.feats-srd.Item.NZgjqVV2HYzLCvvA"
    }
  },
  "effects": [],
  "_stats": {
    "coreVersion": "12.331",
    "systemId": "pf2e",
    "systemVersion": "6.7.2",
    "compendiumSource": "Compendium.pf2e-legacy-content.feats-legacy.Item.NZgjqVV2HYzLCvvA",
    "duplicateSource": null
  },
  "folder": null,
  "sort": 0,
  "ownership": {
    "default": 0
  },
  "_key": "!items!NZgjqVV2HYzLCvvA"
}
