{
  "_id": "jhNkuXg8vJ29GSUJ",
  "img": "systems/pf2e/icons/features/feats/feats.webp",
  "name": "Deep Roots",
  "system": {
    "description": {
      "gm": "",
      "value": "<p>Your mind-control spells send burrowing mental roots that tear at your target's mind when they're removed or run their course. When you Cast a Spell that imposes the @UUID[Compendium.pf2e.conditionitems.Item.9qGBRpbX9NEwtAAr]{Controlled} condition or otherwise forces the target to take certain actions (such as <em>@UUID[Compendium.pf2e.spells-srd.Item.aIHY2DArKFweIrpf]{Command}</em>), you can choose one target that critically failed its save. When that target finishes fulfilling any commands issued by your spell, or when the spell is dispelled or counteracted, the target takes @Damage[1d6[mental]] damage per level of the spell.</p>"
    },
    "rules": [],
    "slug": "deep-roots",
    "_migration": {
      "version": 0.935,
      "lastMigration": null,
      "previous": {
        "schema": 0.879,
        "foundry": "12.331",
        "system": "6.7.2"
      }
    },
    "traits": {
      "otherTags": [],
      "value": [
        "psychic"
      ],
      "rarity": "common"
    },
    "publication": {
      "title": "Pathfinder Dark Archive",
      "authors": "",
      "license": "OGL",
      "remaster": false
    },
    "level": {
      "value": 14
    },
    "category": "class",
    "onlyLevel1": false,
    "maxTakable": 1,
    "actionType": {
      "value": "passive"
    },
    "actions": {
      "value": null
    },
    "prerequisites": {
      "value": []
    },
    "location": null
  },
  "type": "feat",
  "flags": {
    "core": {
      "sourceId": "Compendium.pf2e.feats-srd.Item.jhNkuXg8vJ29GSUJ"
    }
  },
  "effects": [],
  "_stats": {
    "coreVersion": "12.331",
    "systemId": "pf2e",
    "systemVersion": "6.7.2",
    "compendiumSource": "Compendium.pf2e-legacy-content.feats-legacy.Item.jhNkuXg8vJ29GSUJ",
    "duplicateSource": null
  },
  "folder": null,
  "sort": 0,
  "ownership": {
    "default": 0
  },
  "_key": "!items!jhNkuXg8vJ29GSUJ"
}
