{
  "_id": "5AnJTAZnuWrkL8fa",
  "img": "systems/pf2e/icons/features/feats/feats.webp",
  "name": "Defiance Unto Death",
  "system": {
    "description": {
      "gm": "",
      "value": "<p><strong>Access</strong> Spiresworn elf</p>\n<hr />\n<p>You loathe the alghollthus and their mind magic, and you've been trained to be willing to die rather than give into mental manipulation. If you would start your turn @UUID[Compendium.pf2e.conditionitems.Item.yblD8fOR1J8rDwEQ]{Confused}, @UUID[Compendium.pf2e.conditionitems.Item.9qGBRpbX9NEwtAAr]{Controlled}, or @UUID[Compendium.pf2e.conditionitems.Item.sDPxOjQ9kx2RZE8D]{Fleeing} due to a failed Will save, you can attempt a Will save against the same DC; on a success, you become @UUID[Compendium.pf2e.conditionitems.Item.6uEgoh53GbXuHpTF]{Paralyzed} until your next turn, rather than act against your will.</p>"
    },
    "rules": [],
    "slug": "defiance-unto-death",
    "_migration": {
      "version": 0.935,
      "lastMigration": null,
      "previous": {
        "schema": 0.879,
        "foundry": "12.331",
        "system": "6.7.2"
      }
    },
    "traits": {
      "otherTags": [],
      "value": [
        "elf"
      ],
      "rarity": "uncommon"
    },
    "publication": {
      "title": "Pathfinder Lost Omens: Character Guide",
      "authors": "",
      "license": "OGL",
      "remaster": false
    },
    "level": {
      "value": 5
    },
    "category": "ancestry",
    "onlyLevel1": false,
    "maxTakable": 1,
    "actionType": {
      "value": "passive"
    },
    "actions": {
      "value": null
    },
    "prerequisites": {
      "value": []
    },
    "location": null
  },
  "type": "feat",
  "flags": {
    "core": {
      "sourceId": "Compendium.pf2e.feats-srd.Item.5AnJTAZnuWrkL8fa"
    }
  },
  "effects": [],
  "_stats": {
    "coreVersion": "12.331",
    "systemId": "pf2e",
    "systemVersion": "6.7.2",
    "compendiumSource": "Compendium.pf2e-legacy-content.feats-legacy.Item.5AnJTAZnuWrkL8fa",
    "duplicateSource": null
  },
  "folder": null,
  "sort": 0,
  "ownership": {
    "default": 0
  },
  "_key": "!items!5AnJTAZnuWrkL8fa"
}
