{
  "_id": "4n59y5tb9bxffKsi",
  "img": "systems/pf2e/icons/features/feats/feats.webp",
  "name": "Esoteric Reflexes",
  "system": {
    "description": {
      "gm": "",
      "value": "<p>Your bond to your implements is so strong that you can use their reactive abilities almost by instinct. At the start of your turn, you gain an additional reaction, which you can use for only the reactions granted by your implements.</p>"
    },
    "rules": [],
    "slug": "esoteric-reflexes",
    "_migration": {
      "version": 0.935,
      "lastMigration": null,
      "previous": {
        "schema": 0.879,
        "foundry": "12.331",
        "system": "6.7.2"
      }
    },
    "traits": {
      "otherTags": [],
      "value": [
        "thaumaturge"
      ],
      "rarity": "common"
    },
    "publication": {
      "title": "Pathfinder Dark Archive",
      "authors": "",
      "license": "OGL",
      "remaster": false
    },
    "level": {
      "value": 14
    },
    "category": "class",
    "onlyLevel1": false,
    "maxTakable": 1,
    "actionType": {
      "value": "passive"
    },
    "actions": {
      "value": null
    },
    "prerequisites": {
      "value": [
        {
          "value": "an implement that grants a reaction"
        }
      ]
    },
    "location": null
  },
  "type": "feat",
  "flags": {
    "core": {
      "sourceId": "Compendium.pf2e.feats-srd.Item.4n59y5tb9bxffKsi"
    }
  },
  "effects": [],
  "_stats": {
    "coreVersion": "12.331",
    "systemId": "pf2e",
    "systemVersion": "6.7.2",
    "compendiumSource": "Compendium.pf2e-legacy-content.feats-legacy.Item.4n59y5tb9bxffKsi",
    "duplicateSource": null
  },
  "folder": null,
  "sort": 0,
  "ownership": {
    "default": 0
  },
  "_key": "!items!4n59y5tb9bxffKsi"
}
