{
  "_id": "yFoBVSOCnC2R2r8s",
  "img": "systems/pf2e/icons/features/feats/feats.webp",
  "name": "Eternal Composition",
  "system": {
    "description": {
      "gm": "",
      "value": "<p>The world is a stage upon which you are always playing. You are permanently quickened; you can use your extra action only to cast a composition cantrip that requires 1 action to cast. While in exploration mode, you can declare that you are performing an eligible composition cantrip while using any exploration tactic. Even before your first turn in a combat encounter, that cantrip is active as if you had cast it on your previous turn.</p>"
    },
    "rules": [],
    "slug": "eternal-composition",
    "_migration": {
      "version": 0.935,
      "lastMigration": null,
      "previous": {
        "schema": 0.879,
        "foundry": "12.331",
        "system": "6.7.2"
      }
    },
    "traits": {
      "otherTags": [],
      "value": [
        "bard"
      ],
      "rarity": "common"
    },
    "publication": {
      "title": "Pathfinder Core Rulebook",
      "authors": "",
      "license": "OGL",
      "remaster": false
    },
    "level": {
      "value": 18
    },
    "category": "class",
    "onlyLevel1": false,
    "maxTakable": 1,
    "actionType": {
      "value": "passive"
    },
    "actions": {
      "value": null
    },
    "prerequisites": {
      "value": [
        {
          "value": "maestro muse"
        }
      ]
    },
    "location": null
  },
  "type": "feat",
  "flags": {
    "core": {
      "sourceId": "Compendium.pf2e.feats-srd.Item.yFoBVSOCnC2R2r8s"
    }
  },
  "effects": [],
  "_stats": {
    "coreVersion": "12.331",
    "systemId": "pf2e",
    "systemVersion": "6.7.2",
    "compendiumSource": "Compendium.pf2e-legacy-content.feats-legacy.Item.yFoBVSOCnC2R2r8s",
    "duplicateSource": null
  },
  "folder": null,
  "sort": 0,
  "ownership": {
    "default": 0
  },
  "_key": "!items!yFoBVSOCnC2R2r8s"
}
