{
  "_id": "jNrpvEqfncdGZPak",
  "img": "systems/pf2e/icons/features/feats/feats.webp",
  "name": "Halfling Ingenuity",
  "system": {
    "description": {
      "gm": "",
      "value": "<p>While your willingness to dig into a task you know little about might get you into trouble, your incredible luck often saves you from danger. You can attempt skill actions that normally require you to be trained even if you aren't trained in that skill. If you use Halfling Luck when you fail a check for a skill with which you are untrained, you can add a proficiency bonus equal to your level, rather than 0, when you reroll the triggering skill check. You gain a +4 circumstance bonus to this rerolled skill check.</p>"
    },
    "rules": [],
    "slug": "halfling-ingenuity",
    "_migration": {
      "version": 0.935,
      "lastMigration": null,
      "previous": {
        "schema": 0.879,
        "foundry": "12.331",
        "system": "6.7.2"
      }
    },
    "traits": {
      "otherTags": [],
      "value": [
        "halfling"
      ],
      "rarity": "common"
    },
    "publication": {
      "title": "Pathfinder Lost Omens: Character Guide",
      "authors": "",
      "license": "OGL",
      "remaster": false
    },
    "level": {
      "value": 5
    },
    "category": "ancestry",
    "onlyLevel1": false,
    "maxTakable": 1,
    "actionType": {
      "value": "passive"
    },
    "actions": {
      "value": null
    },
    "prerequisites": {
      "value": [
        {
          "value": "Halfling Luck"
        }
      ]
    },
    "location": null
  },
  "type": "feat",
  "flags": {
    "core": {
      "sourceId": "Compendium.pf2e.feats-srd.Item.jNrpvEqfncdGZPak"
    }
  },
  "effects": [],
  "_stats": {
    "coreVersion": "12.331",
    "systemId": "pf2e",
    "systemVersion": "6.7.2",
    "compendiumSource": "Compendium.pf2e-legacy-content.feats-legacy.Item.jNrpvEqfncdGZPak",
    "duplicateSource": null
  },
  "folder": null,
  "sort": 0,
  "ownership": {
    "default": 0
  },
  "_key": "!items!jNrpvEqfncdGZPak"
}
