{
  "prototypeToken": {
    "displayName": 20,
    "displayBars": 20,
    "name": "Dero Magister",
    "actorLink": false,
    "appendNumber": false,
    "prependAdjective": false,
    "width": 1,
    "height": 1,
    "texture": {
      "src": "systems/pf2e/icons/default-icons/npc.svg",
      "anchorX": 0.5,
      "anchorY": 0.5,
      "offsetX": 0,
      "offsetY": 0,
      "fit": "contain",
      "scaleX": 1,
      "scaleY": 1,
      "rotation": 0,
      "tint": "#ffffff",
      "alphaThreshold": 0.75
    },
    "hexagonalShape": 0,
    "lockRotation": false,
    "rotation": 0,
    "alpha": 1,
    "disposition": -1,
    "bar1": {
      "attribute": "attributes.hp"
    },
    "bar2": {
      "attribute": null
    },
    "light": {
      "negative": false,
      "priority": 0,
      "alpha": 0.5,
      "angle": 360,
      "bright": 0,
      "color": null,
      "coloration": 1,
      "dim": 0,
      "attenuation": 0.5,
      "luminosity": 0.5,
      "saturation": 0,
      "contrast": 0,
      "shadows": 0,
      "animation": {
        "type": null,
        "speed": 5,
        "intensity": 5,
        "reverse": false
      },
      "darkness": {
        "min": 0,
        "max": 1
      }
    },
    "sight": {
      "enabled": false,
      "range": 0,
      "angle": 360,
      "visionMode": "basic",
      "color": null,
      "attenuation": 0.1,
      "brightness": 0,
      "saturation": 0,
      "contrast": 0
    },
    "detectionModes": [],
    "occludable": {
      "radius": 0
    },
    "ring": {
      "enabled": false,
      "colors": {
        "ring": null,
        "background": null
      },
      "effects": 1,
      "subject": {
        "scale": 1,
        "texture": null
      }
    },
    "flags": {
      "pf2e": {
        "linkToActorSize": true,
        "autoscale": true
      }
    },
    "randomImg": false
  },
  "_id": "ePa0KmNPpR4zUPfX",
  "img": "systems/pf2e/icons/default-icons/npc.svg",
  "items": [
    {
      "_id": "YuejnaqH1UUSFEtm",
      "img": "systems/pf2e/icons/default-icons/spellcastingEntry.svg",
      "name": "Occult Spontaneous Spells",
      "sort": 100000,
      "system": {
        "description": {
          "gm": "",
          "value": ""
        },
        "rules": [],
        "slug": null,
        "_migration": {
          "version": 0.935,
          "lastMigration": null,
          "previous": {
            "schema": 0.932,
            "foundry": "12.331",
            "system": "6.7.2"
          }
        },
        "traits": {
          "otherTags": []
        },
        "publication": {
          "title": "",
          "authors": "",
          "license": "OGL",
          "remaster": false
        },
        "ability": {
          "value": "cha"
        },
        "spelldc": {
          "value": 16,
          "dc": 24,
          "mod": 0
        },
        "tradition": {
          "value": "occult"
        },
        "prepared": {
          "value": "spontaneous",
          "flexible": false
        },
        "showSlotlessLevels": {
          "value": true
        },
        "proficiency": {
          "value": 0
        },
        "slots": {
          "slot0": {
            "prepared": [],
            "value": 0,
            "max": 0
          },
          "slot1": {
            "prepared": [],
            "value": 4,
            "max": 4
          },
          "slot2": {
            "prepared": [],
            "value": 4,
            "max": 4
          },
          "slot3": {
            "prepared": [],
            "value": 3,
            "max": 3
          },
          "slot4": {
            "prepared": [],
            "value": 0,
            "max": 0
          },
          "slot5": {
            "prepared": [],
            "value": 0,
            "max": 0
          },
          "slot6": {
            "prepared": [],
            "value": 0,
            "max": 0
          },
          "slot7": {
            "prepared": [],
            "value": 0,
            "max": 0
          },
          "slot8": {
            "prepared": [],
            "value": 0,
            "max": 0
          },
          "slot9": {
            "prepared": [],
            "value": 0,
            "max": 0
          },
          "slot10": {
            "prepared": [],
            "value": 0,
            "max": 0
          },
          "slot11": {
            "prepared": [],
            "value": 0,
            "max": 0
          }
        },
        "autoHeightenLevel": {
          "value": null
        }
      },
      "type": "spellcastingEntry",
      "_stats": {
        "compendiumSource": null,
        "duplicateSource": null,
        "coreVersion": "12.331",
        "systemId": "pf2e",
        "systemVersion": "6.7.2"
      },
      "effects": [],
      "folder": null,
      "ownership": {
        "default": 0
      },
      "flags": {},
      "_key": "!actors.items!ePa0KmNPpR4zUPfX.YuejnaqH1UUSFEtm"
    },
    {
      "_id": "bKldotvWkspZfjHv",
      "img": "systems/pf2e/icons/default-icons/spellcastingEntry.svg",
      "name": "Occult Innate Spells",
      "sort": 200000,
      "system": {
        "description": {
          "gm": "",
          "value": ""
        },
        "rules": [],
        "slug": null,
        "_migration": {
          "version": 0.935,
          "lastMigration": null,
          "previous": {
            "schema": 0.932,
            "foundry": "12.331",
            "system": "6.7.2"
          }
        },
        "traits": {
          "otherTags": []
        },
        "publication": {
          "title": "",
          "authors": "",
          "license": "OGL",
          "remaster": false
        },
        "ability": {
          "value": "cha"
        },
        "spelldc": {
          "value": 16,
          "dc": 24,
          "mod": 0
        },
        "tradition": {
          "value": "occult"
        },
        "prepared": {
          "value": "innate",
          "flexible": false
        },
        "showSlotlessLevels": {
          "value": false
        },
        "proficiency": {
          "value": 0
        },
        "slots": {
          "slot0": {
            "prepared": [],
            "value": 0,
            "max": 0
          },
          "slot1": {
            "prepared": [],
            "value": 0,
            "max": 0
          },
          "slot2": {
            "prepared": [],
            "value": 0,
            "max": 0
          },
          "slot3": {
            "prepared": [],
            "value": 0,
            "max": 0
          },
          "slot4": {
            "prepared": [],
            "value": 0,
            "max": 0
          },
          "slot5": {
            "prepared": [],
            "value": 0,
            "max": 0
          },
          "slot6": {
            "prepared": [],
            "value": 0,
            "max": 0
          },
          "slot7": {
            "prepared": [],
            "value": 0,
            "max": 0
          },
          "slot8": {
            "prepared": [],
            "value": 0,
            "max": 0
          },
          "slot9": {
            "prepared": [],
            "value": 0,
            "max": 0
          },
          "slot10": {
            "prepared": [],
            "value": 0,
            "max": 0
          },
          "slot11": {
            "prepared": [],
            "value": 0,
            "max": 0
          }
        },
        "autoHeightenLevel": {
          "value": 1
        }
      },
      "type": "spellcastingEntry",
      "_stats": {
        "compendiumSource": null,
        "duplicateSource": null,
        "coreVersion": "12.331",
        "systemId": "pf2e",
        "systemVersion": "6.7.2"
      },
      "effects": [],
      "folder": null,
      "ownership": {
        "default": 0
      },
      "flags": {},
      "_key": "!actors.items!ePa0KmNPpR4zUPfX.bKldotvWkspZfjHv"
    },
    {
      "_id": "tmYMK1XVL4glUBN6",
      "flags": {
        "core": {
          "sourceId": "Compendium.pf2e.spells-srd.Item.FhOaQDTSnsY7tiam"
        }
      },
      "img": "systems/pf2e/icons/spells/modify-memory.webp",
      "name": "Modify Memory",
      "sort": 300000,
      "system": {
        "description": {
          "gm": "",
          "value": "<p>You alter the target's memories, either erasing a memory, enhancing a memory's clarity, altering a memory, or adding a false memory. The target can attempt a Will save to resist the spell.</p>\n<hr />\n<p><strong>Critical Success</strong> The target is unaffected and realizes you tried to alter its memory.</p>\n<p><strong>Success</strong> The target is unaffected but thinks your spell was something harmless instead of modify memory, unless it identifies the spell.</p>\n<p><strong>Failure</strong> During the first 5 minutes of the spell's duration, you can Sustain the Spell to modify a memory once each round. When you do, you imagine up to 6 seconds of memory to modify, to a maximum of 5 continuous minutes of memory.</p>\n<p>Any memories you've altered remain changed as long as the spell is active. If the target moves out of range before the 5 minutes is up, you can't alter any further memories.</p>\n<hr />\n<p><strong>Heightened (6th)</strong> You can cast the spell on a willing target to suppress all memory of a particular topic, detailed in 50 words or fewer. The effect is permanent, and it patches these omissions with an indistinct haze.</p>"
        },
        "rules": [],
        "slug": "modify-memory",
        "_migration": {
          "version": 0.935,
          "lastMigration": null,
          "previous": {
            "schema": 0.932,
            "foundry": "12.331",
            "system": "6.7.2"
          }
        },
        "traits": {
          "otherTags": [],
          "value": [
            "concentrate",
            "manipulate",
            "mental"
          ],
          "rarity": "uncommon",
          "traditions": [
            "occult"
          ]
        },
        "publication": {
          "title": "Pathfinder Core Rulebook",
          "authors": "",
          "license": "OGL",
          "remaster": false
        },
        "level": {
          "value": 4
        },
        "requirements": "",
        "target": {
          "value": "1 creature"
        },
        "range": {
          "value": "30 feet"
        },
        "area": null,
        "time": {
          "value": "2"
        },
        "duration": {
          "value": "unlimited",
          "sustained": false
        },
        "damage": {},
        "defense": {
          "save": {
            "basic": false,
            "statistic": "will"
          }
        },
        "cost": {
          "value": ""
        },
        "location": {
          "value": "bKldotvWkspZfjHv",
          "heightenedLevel": 4
        },
        "counteraction": false,
        "heightening": {
          "levels": {
            "6": {}
          },
          "type": "fixed"
        }
      },
      "type": "spell",
      "_stats": {
        "compendiumSource": "Compendium.pf2e.spells-srd.Item.FhOaQDTSnsY7tiam",
        "duplicateSource": null,
        "coreVersion": "12.331",
        "systemId": "pf2e",
        "systemVersion": "6.7.2"
      },
      "effects": [],
      "folder": null,
      "ownership": {
        "default": 0
      },
      "_key": "!actors.items!ePa0KmNPpR4zUPfX.tmYMK1XVL4glUBN6"
    },
    {
      "_id": "O27iOfNeQZRvqXtM",
      "flags": {
        "core": {
          "sourceId": "Compendium.pf2e.spells-srd.Item.VosLNn2M8S7JH67D"
        }
      },
      "img": "icons/skills/wounds/injury-eyes-blood-red.webp",
      "name": "Blindness",
      "sort": 400000,
      "system": {
        "description": {
          "gm": "",
          "value": "<p>You blind the target. The effect is determined by the target's Fortitude save. The target then becomes temporarily immune for 1 minute.</p>\n<hr />\n<p><strong>Critical Success</strong> The target is unaffected.</p>\n<p><strong>Success</strong> The target is @UUID[Compendium.pf2e.conditionitems.Item.XgEqL1kFApUbl5Z2]{Blinded} until its next turn begins.</p>\n<p><strong>Failure</strong> The target is Blinded for 1 minute.</p>\n<p><strong>Critical Failure</strong> The target is Blinded permanently.</p>"
        },
        "rules": [],
        "slug": "blindness",
        "_migration": {
          "version": 0.935,
          "lastMigration": null,
          "previous": {
            "schema": 0.932,
            "foundry": "12.331",
            "system": "6.7.2"
          }
        },
        "traits": {
          "otherTags": [],
          "value": [
            "concentrate",
            "incapacitation",
            "manipulate"
          ],
          "rarity": "common",
          "traditions": [
            "arcane",
            "divine",
            "occult",
            "primal"
          ]
        },
        "publication": {
          "title": "Pathfinder Core Rulebook",
          "authors": "",
          "license": "OGL",
          "remaster": false
        },
        "level": {
          "value": 3
        },
        "requirements": "",
        "target": {
          "value": "1 creature"
        },
        "range": {
          "value": "30 feet"
        },
        "area": null,
        "time": {
          "value": "2"
        },
        "duration": {
          "value": "",
          "sustained": false
        },
        "damage": {},
        "defense": {
          "save": {
            "basic": false,
            "statistic": "fortitude"
          }
        },
        "cost": {
          "value": ""
        },
        "location": {
          "value": "YuejnaqH1UUSFEtm",
          "heightenedLevel": 3
        },
        "counteraction": false
      },
      "type": "spell",
      "_stats": {
        "compendiumSource": "Compendium.pf2e.spells-srd.Item.VosLNn2M8S7JH67D",
        "duplicateSource": null,
        "coreVersion": "12.331",
        "systemId": "pf2e",
        "systemVersion": "6.7.2"
      },
      "effects": [],
      "folder": null,
      "ownership": {
        "default": 0
      },
      "_key": "!actors.items!ePa0KmNPpR4zUPfX.O27iOfNeQZRvqXtM"
    },
    {
      "_id": "ktOCZxYYZSbFmO10",
      "flags": {
        "core": {
          "sourceId": "Compendium.pf2e.spells-srd.Item.N1Z1oLPdBxaSgrEE"
        }
      },
      "img": "systems/pf2e/icons/spells/vampiric-touch.webp",
      "name": "Vampiric Touch",
      "sort": 500000,
      "system": {
        "description": {
          "gm": "",
          "value": "<p>Your touch leeches the lifeblood out of a target to empower yourself. You deal 6d6 void damage to the target. You gain temporary Hit Points equal to half the void damage the target takes (after applying resistances and the like). You lose any remaining temporary Hit Points after 1 minute.</p>\n<hr />\n<p><strong>Heightened (+1)</strong> The damage increases by 2d6.</p>"
        },
        "rules": [],
        "slug": "vampiric-touch",
        "_migration": {
          "version": 0.935,
          "lastMigration": null,
          "previous": {
            "schema": 0.932,
            "foundry": "12.331",
            "system": "6.7.2"
          }
        },
        "traits": {
          "otherTags": [],
          "value": [
            "concentrate",
            "death",
            "manipulate",
            "void"
          ],
          "rarity": "common",
          "traditions": [
            "arcane",
            "divine",
            "occult"
          ]
        },
        "publication": {
          "title": "Pathfinder Core Rulebook",
          "authors": "",
          "license": "OGL",
          "remaster": false
        },
        "level": {
          "value": 3
        },
        "requirements": "",
        "target": {
          "value": "1 living creature"
        },
        "range": {
          "value": "touch"
        },
        "area": null,
        "time": {
          "value": "2"
        },
        "duration": {
          "value": "",
          "sustained": false
        },
        "damage": {
          "0": {
            "category": null,
            "formula": "6d6",
            "kinds": [
              "damage"
            ],
            "materials": [],
            "type": "void"
          }
        },
        "defense": {
          "save": {
            "basic": true,
            "statistic": "fortitude"
          }
        },
        "cost": {
          "value": ""
        },
        "location": {
          "value": "YuejnaqH1UUSFEtm",
          "heightenedLevel": 3
        },
        "counteraction": false,
        "heightening": {
          "damage": {
            "0": "2d6"
          },
          "interval": 1,
          "type": "interval"
        }
      },
      "type": "spell",
      "_stats": {
        "compendiumSource": "Compendium.pf2e.spells-srd.Item.N1Z1oLPdBxaSgrEE",
        "duplicateSource": null,
        "coreVersion": "12.331",
        "systemId": "pf2e",
        "systemVersion": "6.7.2"
      },
      "effects": [],
      "folder": null,
      "ownership": {
        "default": 0
      },
      "_key": "!actors.items!ePa0KmNPpR4zUPfX.ktOCZxYYZSbFmO10"
    },
    {
      "_id": "TAYmc59V4sXfSfw5",
      "flags": {
        "core": {
          "sourceId": "Compendium.pf2e.spells-srd.Item.4GE2ZdODgIQtg51c"
        }
      },
      "img": "systems/pf2e/icons/spells/darkness.webp",
      "name": "Darkness (At Will)",
      "sort": 600000,
      "system": {
        "description": {
          "gm": "",
          "value": "<p>You create a shroud of darkness that prevents light from penetrating or emanating within the area. Light does not enter the area and any non-magical light sources, such as a torch or lantern, do not emanate any light while inside the area, even if their light radius would extend beyond the darkness. This also suppresses magical light of your darkness spell's rank or lower. Light can't pass through, so creatures in the area can't see outside. From outside, it appears as a globe of pure darkness.</p>\n<hr />\n<p><strong>Heightened (4th)</strong> Even creatures with darkvision (but not greater darkvision) can barely see through the darkness. They treat targets seen through the darkness as @UUID[Compendium.pf2e.conditionitems.Item.DmAIPqOBomZ7H95W]{Concealed}.</p>"
        },
        "rules": [],
        "slug": "darkness",
        "_migration": {
          "version": 0.935,
          "lastMigration": null,
          "previous": {
            "schema": 0.932,
            "foundry": "12.331",
            "system": "6.7.2"
          }
        },
        "traits": {
          "otherTags": [],
          "value": [
            "concentrate",
            "darkness",
            "manipulate"
          ],
          "rarity": "common",
          "traditions": [
            "arcane",
            "divine",
            "occult",
            "primal"
          ]
        },
        "publication": {
          "title": "Pathfinder Core Rulebook",
          "authors": "",
          "license": "OGL",
          "remaster": false
        },
        "level": {
          "value": 2
        },
        "requirements": "",
        "target": {
          "value": ""
        },
        "range": {
          "value": "120 feet"
        },
        "area": {
          "type": "burst",
          "value": 20
        },
        "time": {
          "value": "3"
        },
        "duration": {
          "value": "1 minute",
          "sustained": false
        },
        "damage": {},
        "defense": null,
        "cost": {
          "value": ""
        },
        "location": {
          "value": "bKldotvWkspZfjHv",
          "heightenedLevel": 2
        },
        "counteraction": false
      },
      "type": "spell",
      "_stats": {
        "compendiumSource": "Compendium.pf2e.spells-srd.Item.4GE2ZdODgIQtg51c",
        "duplicateSource": null,
        "coreVersion": "12.331",
        "systemId": "pf2e",
        "systemVersion": "6.7.2"
      },
      "effects": [],
      "folder": null,
      "ownership": {
        "default": 0
      },
      "_key": "!actors.items!ePa0KmNPpR4zUPfX.TAYmc59V4sXfSfw5"
    },
    {
      "_id": "HkdEGyFCz3KJQDFe",
      "flags": {
        "core": {
          "sourceId": "Compendium.pf2e.spells-srd.Item.tlSE7Ly8vi1Dgddv"
        }
      },
      "img": "systems/pf2e/icons/spells/hideous-laughter.webp",
      "name": "Hideous Laughter",
      "sort": 700000,
      "system": {
        "description": {
          "gm": "",
          "value": "<p>The target is overtaken with uncontrollable laughter. It must attempt a Will save.</p>\n<hr /><p><strong>Critical Success</strong> The target is unaffected.</p>\n<p><strong>Success</strong> The target is plagued with uncontrollable laughter. It can't use reactions.</p>\n<p><strong>Failure</strong> The target is @UUID[Compendium.pf2e.conditionitems.Item.xYTAsEpcJE1Ccni3]{Slowed 1} and can't use reactions.</p>\n<p><strong>Critical Failure</strong> The target falls @UUID[Compendium.pf2e.conditionitems.Item.j91X7x0XSomq8d60]{Prone} and can't use actions or reactions for 1 round. It then suffers the failure effects.</p>"
        },
        "rules": [],
        "slug": "hideous-laughter",
        "_migration": {
          "version": 0.935,
          "lastMigration": null,
          "previous": {
            "schema": 0.932,
            "foundry": "12.331",
            "system": "6.7.2"
          }
        },
        "traits": {
          "otherTags": [],
          "value": [
            "concentrate",
            "emotion",
            "manipulate",
            "mental"
          ],
          "rarity": "common",
          "traditions": [
            "arcane",
            "occult"
          ]
        },
        "publication": {
          "title": "Pathfinder Core Rulebook",
          "authors": "",
          "license": "OGL",
          "remaster": false
        },
        "level": {
          "value": 2
        },
        "requirements": "",
        "target": {
          "value": "1 living creature"
        },
        "range": {
          "value": "30 feet"
        },
        "area": null,
        "time": {
          "value": "2"
        },
        "duration": {
          "value": "",
          "sustained": true
        },
        "damage": {},
        "defense": {
          "save": {
            "basic": false,
            "statistic": "will"
          }
        },
        "cost": {
          "value": ""
        },
        "location": {
          "value": "YuejnaqH1UUSFEtm",
          "heightenedLevel": 2
        },
        "counteraction": false
      },
      "type": "spell",
      "_stats": {
        "compendiumSource": "Compendium.pf2e.spells-srd.Item.tlSE7Ly8vi1Dgddv",
        "duplicateSource": null,
        "coreVersion": "12.331",
        "systemId": "pf2e",
        "systemVersion": "6.7.2"
      },
      "effects": [],
      "folder": null,
      "ownership": {
        "default": 0
      },
      "_key": "!actors.items!ePa0KmNPpR4zUPfX.HkdEGyFCz3KJQDFe"
    },
    {
      "_id": "LGQ2ibpBXbZjiSBO",
      "flags": {
        "core": {
          "sourceId": "Compendium.pf2e.spells-srd.Item.Mkbq9xlAUxHUHyR2"
        }
      },
      "img": "icons/magic/fire/flame-burning-eye.webp",
      "name": "Paranoia",
      "sort": 800000,
      "system": {
        "description": {
          "gm": "",
          "value": "<p>You cause the target to see all other creatures as dire threats. The target is stricken by intense paranoia toward all creatures around it and must attempt a Will save.</p>\n<hr /><p><strong>Critical Success</strong> The target is unaffected.</p>\n<p><strong>Success</strong> The target believes everyone it sees is a potential threat. It becomes @UUID[Compendium.pf2e.conditionitems.Item.I1ffBVISxLr2gC4u]{Unfriendly} to all creatures to which it wasn't already hostile, even those that were previously allies. It treats no one as an ally. The spell ends after 1 round.</p>\n<p><strong>Failure</strong> As success, but the effect lasts 1 minute.</p>\n<p><strong>Critical Failure</strong> As failure, except the target believes that everyone it sees is a mortal enemy. It uses its reactions and free actions against everyone, regardless of whether they were previously its allies, as determined by the GM. It otherwise acts as rationally as it normally does and likely prefers to attack creatures that are actively attacking or hindering it over those leaving it alone.</p>\n<hr /><p><strong>Heightened (6th)</strong> You can target up to 5 creatures.</p>"
        },
        "rules": [],
        "slug": "paranoia",
        "_migration": {
          "version": 0.935,
          "lastMigration": null,
          "previous": {
            "schema": 0.932,
            "foundry": "12.331",
            "system": "6.7.2"
          }
        },
        "traits": {
          "otherTags": [],
          "value": [
            "concentrate",
            "illusion",
            "manipulate",
            "mental"
          ],
          "rarity": "common",
          "traditions": [
            "occult"
          ]
        },
        "publication": {
          "title": "Pathfinder Core Rulebook",
          "authors": "",
          "license": "OGL",
          "remaster": false
        },
        "level": {
          "value": 2
        },
        "requirements": "",
        "target": {
          "value": "1 creature"
        },
        "range": {
          "value": "30 feet"
        },
        "area": null,
        "time": {
          "value": "2"
        },
        "duration": {
          "value": "1 minute",
          "sustained": false
        },
        "damage": {},
        "defense": {
          "save": {
            "basic": false,
            "statistic": "will"
          }
        },
        "cost": {
          "value": ""
        },
        "location": {
          "value": "YuejnaqH1UUSFEtm",
          "heightenedLevel": 2
        },
        "counteraction": false,
        "heightening": {
          "levels": {
            "6": {
              "target": {
                "value": "5 creatures"
              }
            }
          },
          "type": "fixed"
        }
      },
      "type": "spell",
      "_stats": {
        "compendiumSource": "Compendium.pf2e.spells-srd.Item.Mkbq9xlAUxHUHyR2",
        "duplicateSource": null,
        "coreVersion": "12.331",
        "systemId": "pf2e",
        "systemVersion": "6.7.2"
      },
      "effects": [],
      "folder": null,
      "ownership": {
        "default": 0
      },
      "_key": "!actors.items!ePa0KmNPpR4zUPfX.LGQ2ibpBXbZjiSBO"
    },
    {
      "_id": "TuM7xwEDIHACG7NZ",
      "flags": {
        "core": {
          "sourceId": "Compendium.pf2e.spells-srd.Item.wzLkNU3AAqOSKFPR"
        }
      },
      "img": "icons/magic/fire/orb-vortex.webp",
      "name": "Sound Burst",
      "sort": 900000,
      "system": {
        "description": {
          "gm": "",
          "value": "<p>A cacophonous noise blasts out, dealing 2d10 sonic damage. Each creature must attempt a Fortitude save.</p>\n<hr />\n<p><strong>Critical Success</strong> The creature is unaffected.</p>\n<p><strong>Success</strong> The creature takes half damage.</p>\n<p><strong>Failure</strong> The creature takes full damage and is @UUID[Compendium.pf2e.conditionitems.Item.9PR9y0bi4JPKnHPR]{Deafened} for 1 round.</p>\n<p><strong>Critical Failure</strong> The creature takes double damage, is Deafened for 1 minute, and is @UUID[Compendium.pf2e.conditionitems.Item.dfCMdR4wnpbYNTix]{Stunned 1}.</p>\n<hr />\n<p><strong>Heightened (+1)</strong> The damage increases by 1d10.</p>"
        },
        "rules": [],
        "slug": "sound-burst",
        "_migration": {
          "version": 0.935,
          "lastMigration": null,
          "previous": {
            "schema": 0.932,
            "foundry": "12.331",
            "system": "6.7.2"
          }
        },
        "traits": {
          "otherTags": [],
          "value": [
            "concentrate",
            "manipulate",
            "sonic"
          ],
          "rarity": "common",
          "traditions": [
            "divine",
            "occult"
          ]
        },
        "publication": {
          "title": "Pathfinder Core Rulebook",
          "authors": "",
          "license": "OGL",
          "remaster": false
        },
        "level": {
          "value": 2
        },
        "requirements": "",
        "target": {
          "value": ""
        },
        "range": {
          "value": "30 feet"
        },
        "area": {
          "type": "burst",
          "value": 10
        },
        "time": {
          "value": "2"
        },
        "duration": {
          "value": "",
          "sustained": false
        },
        "damage": {
          "0": {
            "category": null,
            "formula": "2d10",
            "kinds": [
              "damage"
            ],
            "materials": [],
            "type": "sonic"
          }
        },
        "defense": {
          "save": {
            "basic": false,
            "statistic": "fortitude"
          }
        },
        "cost": {
          "value": ""
        },
        "location": {
          "value": "bKldotvWkspZfjHv",
          "heightenedLevel": 2
        },
        "counteraction": false,
        "heightening": {
          "damage": {
            "0": "1d10"
          },
          "interval": 1,
          "type": "interval"
        }
      },
      "type": "spell",
      "_stats": {
        "compendiumSource": "Compendium.pf2e.spells-srd.Item.wzLkNU3AAqOSKFPR",
        "duplicateSource": null,
        "coreVersion": "12.331",
        "systemId": "pf2e",
        "systemVersion": "6.7.2"
      },
      "effects": [],
      "folder": null,
      "ownership": {
        "default": 0
      },
      "_key": "!actors.items!ePa0KmNPpR4zUPfX.TuM7xwEDIHACG7NZ"
    },
    {
      "_id": "q6YTPtO71XZsmIBT",
      "flags": {
        "core": {
          "sourceId": "Compendium.pf2e.spells-srd.Item.rthC6dGm3nNrt1xN"
        }
      },
      "img": "systems/pf2e/icons/spells/spectral-hand.webp",
      "name": "Spectral Hand",
      "sort": 1000000,
      "system": {
        "description": {
          "gm": "",
          "value": "<p>You create a semicorporeal hand out of your essence that delivers touch spells for you. Whenever you Cast a Spell with a range of touch, you can have the hand crawl to a target within range along the ground, touch it, and then crawl back to you. When making a melee spell attack with the hand, you use your normal bonuses. The hand can move as far as it needs to within range. The hand has your AC and saves, but any damage to the hand destroys it and causes you to take 1d6 damage.</p>"
        },
        "rules": [],
        "slug": "spectral-hand",
        "_migration": {
          "version": 0.935,
          "lastMigration": null,
          "previous": {
            "schema": 0.932,
            "foundry": "12.331",
            "system": "6.7.2"
          }
        },
        "traits": {
          "otherTags": [],
          "value": [
            "concentrate",
            "manipulate"
          ],
          "rarity": "common",
          "traditions": [
            "arcane",
            "occult"
          ]
        },
        "publication": {
          "title": "Pathfinder Core Rulebook",
          "authors": "",
          "license": "OGL",
          "remaster": false
        },
        "level": {
          "value": 2
        },
        "requirements": "",
        "target": {
          "value": ""
        },
        "range": {
          "value": "120 feet"
        },
        "area": null,
        "time": {
          "value": "2"
        },
        "duration": {
          "value": "1 minute",
          "sustained": false
        },
        "damage": {},
        "defense": null,
        "cost": {
          "value": ""
        },
        "location": {
          "value": "YuejnaqH1UUSFEtm",
          "heightenedLevel": 2
        },
        "counteraction": false
      },
      "type": "spell",
      "_stats": {
        "compendiumSource": "Compendium.pf2e.spells-srd.Item.rthC6dGm3nNrt1xN",
        "duplicateSource": null,
        "coreVersion": "12.331",
        "systemId": "pf2e",
        "systemVersion": "6.7.2"
      },
      "effects": [],
      "folder": null,
      "ownership": {
        "default": 0
      },
      "_key": "!actors.items!ePa0KmNPpR4zUPfX.q6YTPtO71XZsmIBT"
    },
    {
      "_id": "1kBYCVWKgh7Adoob",
      "flags": {
        "core": {
          "sourceId": "Compendium.pf2e.spells-srd.Item.CQb8HtQ1BPeZmu9h"
        }
      },
      "img": "systems/pf2e/icons/spells/touch-of-idiocy.webp",
      "name": "Touch of Idiocy",
      "sort": 1100000,
      "system": {
        "description": {
          "gm": "",
          "value": "<p>You dull the target's mind; the target must attempt a Will save.</p>\n<hr />\n<p><strong>Success</strong> The target is unaffected.</p>\n<p><strong>Failure</strong> The target is @UUID[Compendium.pf2e.conditionitems.Item.e1XGnhKNSQIm5IXg]{Stupefied 2}.</p>\n<p><strong>Critical Failure</strong> The target is @UUID[Compendium.pf2e.conditionitems.Item.e1XGnhKNSQIm5IXg]{Stupefied 4}.</p>"
        },
        "rules": [],
        "slug": "touch-of-idiocy",
        "_migration": {
          "version": 0.935,
          "lastMigration": null,
          "previous": {
            "schema": 0.932,
            "foundry": "12.331",
            "system": "6.7.2"
          }
        },
        "traits": {
          "otherTags": [],
          "value": [
            "concentrate",
            "manipulate",
            "mental"
          ],
          "rarity": "common",
          "traditions": [
            "arcane",
            "occult"
          ]
        },
        "publication": {
          "title": "Pathfinder Core Rulebook",
          "authors": "",
          "license": "OGL",
          "remaster": false
        },
        "level": {
          "value": 2
        },
        "requirements": "",
        "target": {
          "value": "1 living creature"
        },
        "range": {
          "value": "touch"
        },
        "area": null,
        "time": {
          "value": "2"
        },
        "duration": {
          "value": "1 minute",
          "sustained": false
        },
        "damage": {},
        "defense": {
          "save": {
            "basic": false,
            "statistic": "will"
          }
        },
        "cost": {
          "value": ""
        },
        "location": {
          "value": "YuejnaqH1UUSFEtm",
          "heightenedLevel": 2
        },
        "counteraction": false
      },
      "type": "spell",
      "_stats": {
        "compendiumSource": "Compendium.pf2e.spells-srd.Item.CQb8HtQ1BPeZmu9h",
        "duplicateSource": null,
        "coreVersion": "12.331",
        "systemId": "pf2e",
        "systemVersion": "6.7.2"
      },
      "effects": [],
      "folder": null,
      "ownership": {
        "default": 0
      },
      "_key": "!actors.items!ePa0KmNPpR4zUPfX.1kBYCVWKgh7Adoob"
    },
    {
      "_id": "OmcfUYyCkGRjSKmB",
      "flags": {
        "core": {
          "sourceId": "Compendium.pf2e.spells-srd.Item.mAMEt4FFbdqoRnkN"
        }
      },
      "img": "systems/pf2e/icons/spells/chill-touch.webp",
      "name": "Chill Touch",
      "sort": 1200000,
      "system": {
        "description": {
          "gm": "",
          "value": "<p>Siphoning void energy into yourself, your hand radiates a pale darkness. Your touch weakens the living and disorients undead, possibly even causing them to flee. The effect depends on whether the target is living or undead.</p>\n<ul>\n<li><strong>Living Creature</strong> The spell deals void damage equal to 1d4 plus your spellcasting modifier. The target attempts a basic Fortitude save, but is also @UUID[Compendium.pf2e.conditionitems.Item.MIRkyAjyBeXivMa7]{Enfeebled 1} for 1 round on a critical failure.</li>\n<li><strong>Undead Creature</strong> The target is @UUID[Compendium.pf2e.conditionitems.Item.AJh5ex99aV6VTggg]{Off-Guard} for 1 round on a failed Fortitude save. On a critical failure, the target is also @UUID[Compendium.pf2e.conditionitems.Item.sDPxOjQ9kx2RZE8D]{Fleeing} for 1 round unless it succeeds at a Will save.</li>\n</ul>\n<hr />\n<p><strong>Heightened (+1)</strong> The void damage to living creatures increases by 1d4.</p>"
        },
        "rules": [],
        "slug": "chill-touch",
        "_migration": {
          "version": 0.935,
          "lastMigration": null,
          "previous": {
            "schema": 0.932,
            "foundry": "12.331",
            "system": "6.7.2"
          }
        },
        "traits": {
          "otherTags": [],
          "value": [
            "cantrip",
            "concentrate",
            "manipulate",
            "void"
          ],
          "rarity": "common",
          "traditions": [
            "arcane",
            "divine",
            "occult"
          ]
        },
        "publication": {
          "title": "Pathfinder Core Rulebook",
          "authors": "",
          "license": "OGL",
          "remaster": false
        },
        "level": {
          "value": 1
        },
        "requirements": "",
        "target": {
          "value": "1 living or undead creature"
        },
        "range": {
          "value": "touch"
        },
        "area": null,
        "time": {
          "value": "2"
        },
        "duration": {
          "value": "",
          "sustained": false
        },
        "damage": {
          "0": {
            "applyMod": true,
            "category": null,
            "formula": "1d4",
            "kinds": [
              "damage"
            ],
            "materials": [],
            "type": "void"
          }
        },
        "defense": {
          "save": {
            "basic": true,
            "statistic": "fortitude"
          }
        },
        "cost": {
          "value": ""
        },
        "location": {
          "value": "YuejnaqH1UUSFEtm"
        },
        "counteraction": false,
        "heightening": {
          "damage": {
            "0": "1d4"
          },
          "interval": 1,
          "type": "interval"
        }
      },
      "type": "spell",
      "_stats": {
        "compendiumSource": "Compendium.pf2e.spells-srd.Item.mAMEt4FFbdqoRnkN",
        "duplicateSource": null,
        "coreVersion": "12.331",
        "systemId": "pf2e",
        "systemVersion": "6.7.2"
      },
      "effects": [],
      "folder": null,
      "ownership": {
        "default": 0
      },
      "_key": "!actors.items!ePa0KmNPpR4zUPfX.OmcfUYyCkGRjSKmB"
    },
    {
      "_id": "cIbdrH5jcFj8t5ik",
      "flags": {
        "core": {
          "sourceId": "Compendium.pf2e.spells-srd.Item.kl2q6JvBZwed4B6v"
        }
      },
      "img": "systems/pf2e/icons/spells/dancing-lights.webp",
      "name": "Dancing Lights",
      "sort": 1300000,
      "system": {
        "description": {
          "gm": "",
          "value": "<p>You create up to four floating lights, no two of which are more than 10 feet apart. Each sheds light like a torch. When you Sustain the Spell, you can move any number of lights up to 60 feet. Each light must remain within 120 feet of you and within 10 feet of all others, or it winks out.</p>"
        },
        "rules": [],
        "slug": "dancing-lights",
        "_migration": {
          "version": 0.935,
          "lastMigration": null,
          "previous": {
            "schema": 0.932,
            "foundry": "12.331",
            "system": "6.7.2"
          }
        },
        "traits": {
          "otherTags": [],
          "value": [
            "cantrip",
            "concentrate",
            "light",
            "manipulate"
          ],
          "rarity": "common",
          "traditions": [
            "arcane",
            "occult",
            "primal"
          ]
        },
        "publication": {
          "title": "Pathfinder Core Rulebook",
          "authors": "",
          "license": "OGL",
          "remaster": false
        },
        "level": {
          "value": 1
        },
        "requirements": "",
        "target": {
          "value": ""
        },
        "range": {
          "value": "120 feet"
        },
        "area": null,
        "time": {
          "value": "2"
        },
        "duration": {
          "value": "",
          "sustained": true
        },
        "damage": {},
        "defense": null,
        "cost": {
          "value": ""
        },
        "location": {
          "value": "YuejnaqH1UUSFEtm"
        },
        "counteraction": false
      },
      "type": "spell",
      "_stats": {
        "compendiumSource": "Compendium.pf2e.spells-srd.Item.kl2q6JvBZwed4B6v",
        "duplicateSource": null,
        "coreVersion": "12.331",
        "systemId": "pf2e",
        "systemVersion": "6.7.2"
      },
      "effects": [],
      "folder": null,
      "ownership": {
        "default": 0
      },
      "_key": "!actors.items!ePa0KmNPpR4zUPfX.cIbdrH5jcFj8t5ik"
    },
    {
      "_id": "p8EZCiPuYDGVa8gR",
      "flags": {
        "core": {
          "sourceId": "Compendium.pf2e.spells-srd.Item.4gBIw4IDrSfFHik4"
        }
      },
      "img": "systems/pf2e/icons/spells/daze.webp",
      "name": "Daze",
      "sort": 1400000,
      "system": {
        "description": {
          "gm": "",
          "value": "<p>You cloud the target's mind and daze it with a mental jolt. The jolt deals mental damage equal to your spellcasting ability modifier; the target must attempt a basic Will save. If the target critically fails the save, it is also @UUID[Compendium.pf2e.conditionitems.Item.dfCMdR4wnpbYNTix]{Stunned 1}.</p>\n<hr />\n<p><strong>Heightened (+2)</strong> The damage increases by 1d6.</p>"
        },
        "rules": [],
        "slug": "daze",
        "_migration": {
          "version": 0.935,
          "lastMigration": null,
          "previous": {
            "schema": 0.932,
            "foundry": "12.331",
            "system": "6.7.2"
          }
        },
        "traits": {
          "otherTags": [],
          "value": [
            "cantrip",
            "concentrate",
            "manipulate",
            "mental",
            "nonlethal"
          ],
          "rarity": "common",
          "traditions": [
            "arcane",
            "divine",
            "occult"
          ]
        },
        "publication": {
          "title": "Pathfinder Core Rulebook",
          "authors": "",
          "license": "OGL",
          "remaster": false
        },
        "level": {
          "value": 1
        },
        "requirements": "",
        "target": {
          "value": "1 creature"
        },
        "range": {
          "value": "60 feet"
        },
        "area": null,
        "time": {
          "value": "2"
        },
        "duration": {
          "value": "1 round",
          "sustained": false
        },
        "damage": {
          "0": {
            "applyMod": true,
            "category": null,
            "formula": "0",
            "kinds": [
              "damage"
            ],
            "materials": [],
            "type": "mental"
          }
        },
        "defense": {
          "save": {
            "basic": true,
            "statistic": "will"
          }
        },
        "cost": {
          "value": ""
        },
        "location": {
          "value": "bKldotvWkspZfjHv"
        },
        "counteraction": false,
        "heightening": {
          "damage": {
            "0": "1d6"
          },
          "interval": 2,
          "type": "interval"
        }
      },
      "type": "spell",
      "_stats": {
        "compendiumSource": "Compendium.pf2e.spells-srd.Item.4gBIw4IDrSfFHik4",
        "duplicateSource": null,
        "coreVersion": "12.331",
        "systemId": "pf2e",
        "systemVersion": "6.7.2"
      },
      "effects": [],
      "folder": null,
      "ownership": {
        "default": 0
      },
      "_key": "!actors.items!ePa0KmNPpR4zUPfX.p8EZCiPuYDGVa8gR"
    },
    {
      "_id": "Va0XfogT4F60cFwg",
      "flags": {
        "core": {
          "sourceId": "Compendium.pf2e.spells-srd.Item.gpzpAAAJ1Lza2JVl"
        }
      },
      "img": "systems/pf2e/icons/spells/detect-magic.webp",
      "name": "Detect Magic",
      "sort": 1500000,
      "system": {
        "description": {
          "gm": "",
          "value": "<p>You send out a pulse that registers the presence of magic. You receive no information beyond the presence or absence of magic. You can choose to ignore magic you're fully aware of, such as the magic items and ongoing spells of you and your allies.</p>\n<p>You detect illusion magic only if that magic's effect has a lower level than the rank of your detect magic spell. However, items that have an illusion aura but aren't deceptive in appearance (such as an invisibility potion) typically are detected normally.</p>\n<hr />\n<p><strong>Heightened (3rd)</strong> You learn the school of magic for the highest-level effect within range that the spell detects. If multiple effects are equally strong, the GM determines which you learn.</p>\n<p><strong>Heightened (4th)</strong> As 3rd level, but you also pinpoint the source of the highest-level magic. Like for an imprecise sense, you don't learn the exact location, but can narrow down the source to within a 5-foot cube (or the nearest if larger than that).</p>"
        },
        "rules": [],
        "slug": "detect-magic",
        "_migration": {
          "version": 0.935,
          "lastMigration": null,
          "previous": {
            "schema": 0.932,
            "foundry": "12.331",
            "system": "6.7.2"
          }
        },
        "traits": {
          "otherTags": [],
          "value": [
            "cantrip",
            "concentrate",
            "detection",
            "manipulate"
          ],
          "rarity": "common",
          "traditions": [
            "arcane",
            "divine",
            "occult",
            "primal"
          ]
        },
        "publication": {
          "title": "Pathfinder Core Rulebook",
          "authors": "",
          "license": "OGL",
          "remaster": false
        },
        "level": {
          "value": 1
        },
        "requirements": "",
        "target": {
          "value": ""
        },
        "range": {
          "value": ""
        },
        "area": {
          "type": "emanation",
          "value": 30
        },
        "time": {
          "value": "2"
        },
        "duration": {
          "value": "",
          "sustained": false
        },
        "damage": {},
        "defense": null,
        "cost": {
          "value": ""
        },
        "location": {
          "value": "YuejnaqH1UUSFEtm"
        },
        "counteraction": false
      },
      "type": "spell",
      "_stats": {
        "compendiumSource": "Compendium.pf2e.spells-srd.Item.gpzpAAAJ1Lza2JVl",
        "duplicateSource": null,
        "coreVersion": "12.331",
        "systemId": "pf2e",
        "systemVersion": "6.7.2"
      },
      "effects": [],
      "folder": null,
      "ownership": {
        "default": 0
      },
      "_key": "!actors.items!ePa0KmNPpR4zUPfX.Va0XfogT4F60cFwg"
    },
    {
      "_id": "qfUlje8uIZvyiwdl",
      "flags": {
        "core": {
          "sourceId": "Compendium.pf2e.spells-srd.Item.RA7VKcen3p56rVyZ"
        }
      },
      "img": "systems/pf2e/icons/spells/forbidding-ward.webp",
      "name": "Forbidding Ward",
      "sort": 1600000,
      "system": {
        "description": {
          "gm": "",
          "value": "<p>You ward an ally against the attacks and hostile spells from the target enemy. The target ally gains a +1 status bonus to Armor Class and saving throws against the target enemy's attacks, spells, and other effects.</p>\n<p>@UUID[Compendium.pf2e.spell-effects.Item.ctMxYPGEpstvhW9C]{Spell Effect: Forbidding Ward}</p>\n<hr />\n<p><strong>Heightened (6th)</strong> The status bonus increases to +2.</p>"
        },
        "rules": [],
        "slug": "forbidding-ward",
        "_migration": {
          "version": 0.935,
          "lastMigration": null,
          "previous": {
            "schema": 0.932,
            "foundry": "12.331",
            "system": "6.7.2"
          }
        },
        "traits": {
          "otherTags": [],
          "value": [
            "cantrip",
            "concentrate",
            "manipulate"
          ],
          "rarity": "common",
          "traditions": [
            "divine",
            "occult"
          ]
        },
        "publication": {
          "title": "Pathfinder Core Rulebook",
          "authors": "",
          "license": "OGL",
          "remaster": false
        },
        "level": {
          "value": 1
        },
        "requirements": "",
        "target": {
          "value": "1 ally and 1 enemy"
        },
        "range": {
          "value": "30 feet"
        },
        "area": null,
        "time": {
          "value": "2"
        },
        "duration": {
          "value": "1 minute",
          "sustained": true
        },
        "damage": {},
        "defense": null,
        "cost": {
          "value": ""
        },
        "location": {
          "value": "YuejnaqH1UUSFEtm"
        },
        "counteraction": false
      },
      "type": "spell",
      "_stats": {
        "compendiumSource": "Compendium.pf2e.spells-srd.Item.RA7VKcen3p56rVyZ",
        "duplicateSource": null,
        "coreVersion": "12.331",
        "systemId": "pf2e",
        "systemVersion": "6.7.2"
      },
      "effects": [],
      "folder": null,
      "ownership": {
        "default": 0
      },
      "_key": "!actors.items!ePa0KmNPpR4zUPfX.qfUlje8uIZvyiwdl"
    },
    {
      "_id": "Gw1aL6nvi3vctrVz",
      "flags": {
        "core": {
          "sourceId": "Compendium.pf2e.spells-srd.Item.atlgGNI1E1Ox3O3a"
        }
      },
      "img": "systems/pf2e/icons/spells/ghost-sound.webp",
      "name": "Ghost Sound",
      "sort": 1700000,
      "system": {
        "description": {
          "gm": "",
          "value": "<p>You create an auditory illusion of simple sounds that has a maximum volume equal to four normal humans shouting. The sounds emanate from a square you designate within range. You can't create intelligible words or other intricate sounds (such as music).</p>\n<hr />\n<p><strong>Heightened (3rd)</strong> The range increases to 60 feet.</p>\n<p><strong>Heightened (5th)</strong> The range increases to 120 feet.</p>"
        },
        "rules": [],
        "slug": "ghost-sound",
        "_migration": {
          "version": 0.935,
          "lastMigration": null,
          "previous": {
            "schema": 0.932,
            "foundry": "12.331",
            "system": "6.7.2"
          }
        },
        "traits": {
          "otherTags": [],
          "value": [
            "auditory",
            "cantrip",
            "concentrate",
            "illusion",
            "manipulate"
          ],
          "rarity": "common",
          "traditions": [
            "arcane",
            "occult"
          ]
        },
        "publication": {
          "title": "Pathfinder Core Rulebook",
          "authors": "",
          "license": "OGL",
          "remaster": false
        },
        "level": {
          "value": 1
        },
        "requirements": "",
        "target": {
          "value": ""
        },
        "range": {
          "value": "30 feet"
        },
        "area": null,
        "time": {
          "value": "2"
        },
        "duration": {
          "value": "",
          "sustained": true
        },
        "damage": {},
        "defense": null,
        "cost": {
          "value": ""
        },
        "location": {
          "value": "bKldotvWkspZfjHv"
        },
        "counteraction": false,
        "heightening": {
          "levels": {
            "3": {
              "range": {
                "value": "60 feet"
              }
            },
            "5": {
              "range": {
                "value": "120 feet"
              }
            }
          },
          "type": "fixed"
        }
      },
      "type": "spell",
      "_stats": {
        "compendiumSource": "Compendium.pf2e.spells-srd.Item.atlgGNI1E1Ox3O3a",
        "duplicateSource": null,
        "coreVersion": "12.331",
        "systemId": "pf2e",
        "systemVersion": "6.7.2"
      },
      "effects": [],
      "folder": null,
      "ownership": {
        "default": 0
      },
      "_key": "!actors.items!ePa0KmNPpR4zUPfX.Gw1aL6nvi3vctrVz"
    },
    {
      "_id": "rlUeL3r4Q1tTG2zt",
      "flags": {
        "core": {
          "sourceId": "Compendium.pf2e.spells-srd.Item.k34hDOfIIMAxNL4a"
        }
      },
      "img": "systems/pf2e/icons/spells/grim-tendrils.webp",
      "name": "Grim Tendrils",
      "sort": 1800000,
      "system": {
        "description": {
          "gm": "",
          "value": "<p>Tendrils of darkness curl out from your fingertips and race through the air. You deal 2d4 void damage and [[/r (@item.level)[bleed]]] damage to living creatures in the line. Each living creature in the line must attempt a Fortitude save.</p>\n<hr />\n<p><strong>Critical Success</strong> The creature is unaffected.</p>\n<p><strong>Success</strong> The creature takes half the void damage and no persistent bleed damage.</p>\n<p><strong>Failure</strong> The creature takes full damage.</p>\n<p><strong>Critical Failure</strong> The creature takes double void damage and double persistent bleed damage.</p>\n<hr />\n<p><strong>Heightened (+1)</strong> The void damage increases by 2d4, and the persistent bleed damage increases by 1.</p>"
        },
        "rules": [],
        "slug": "grim-tendrils",
        "_migration": {
          "version": 0.935,
          "lastMigration": null,
          "previous": {
            "schema": 0.932,
            "foundry": "12.331",
            "system": "6.7.2"
          }
        },
        "traits": {
          "otherTags": [],
          "value": [
            "concentrate",
            "manipulate",
            "void"
          ],
          "rarity": "common",
          "traditions": [
            "arcane",
            "occult"
          ]
        },
        "publication": {
          "title": "Pathfinder Core Rulebook",
          "authors": "",
          "license": "OGL",
          "remaster": false
        },
        "level": {
          "value": 1
        },
        "requirements": "",
        "target": {
          "value": ""
        },
        "range": {
          "value": ""
        },
        "area": {
          "type": "line",
          "value": 30
        },
        "time": {
          "value": "2"
        },
        "duration": {
          "value": "",
          "sustained": false
        },
        "damage": {
          "0": {
            "applyMod": false,
            "category": null,
            "formula": "2d4",
            "kinds": [
              "damage"
            ],
            "materials": [],
            "type": "void"
          }
        },
        "defense": {
          "save": {
            "basic": false,
            "statistic": "fortitude"
          }
        },
        "cost": {
          "value": ""
        },
        "location": {
          "value": "YuejnaqH1UUSFEtm",
          "heightenedLevel": 1
        },
        "counteraction": false,
        "heightening": {
          "damage": {
            "0": "2d4"
          },
          "interval": 1,
          "type": "interval"
        }
      },
      "type": "spell",
      "_stats": {
        "compendiumSource": "Compendium.pf2e.spells-srd.Item.k34hDOfIIMAxNL4a",
        "duplicateSource": null,
        "coreVersion": "12.331",
        "systemId": "pf2e",
        "systemVersion": "6.7.2"
      },
      "effects": [],
      "folder": null,
      "ownership": {
        "default": 0
      },
      "_key": "!actors.items!ePa0KmNPpR4zUPfX.rlUeL3r4Q1tTG2zt"
    },
    {
      "_id": "LJv30DGfMEFT9EHc",
      "flags": {
        "core": {
          "sourceId": "Compendium.pf2e.spells-srd.Item.gKKqvLohtrSJj3BM"
        }
      },
      "img": "systems/pf2e/icons/spells/magic-missile.webp",
      "name": "Magic Missile",
      "sort": 1900000,
      "system": {
        "description": {
          "gm": "",
          "value": "<p>You send a dart of force streaking toward a creature that you can see. It automatically hits and deals 1d4+1 force damage. For each additional action you use when Casting the Spell, increase the number of missiles you shoot by one, to a maximum of three missiles for 3 actions. You choose the target for each missile individually. If you shoot more than one missile at the same target, combine the damage before applying bonuses or penalties to damage, resistances, weaknesses, and so forth.</p>\n<hr />\n<p><strong>Heightened (+2)</strong> You shoot one additional missile with each action you spend.</p>"
        },
        "rules": [],
        "slug": "magic-missile",
        "_migration": {
          "version": 0.935,
          "lastMigration": null,
          "previous": {
            "schema": 0.932,
            "foundry": "12.331",
            "system": "6.7.2"
          }
        },
        "traits": {
          "otherTags": [],
          "value": [
            "concentrate",
            "force",
            "manipulate"
          ],
          "rarity": "common",
          "traditions": [
            "arcane",
            "occult"
          ]
        },
        "publication": {
          "title": "Pathfinder Core Rulebook",
          "authors": "",
          "license": "OGL",
          "remaster": false
        },
        "level": {
          "value": 1
        },
        "requirements": "",
        "target": {
          "value": "1 creature"
        },
        "range": {
          "value": "120 feet"
        },
        "area": null,
        "time": {
          "value": "1 to 3"
        },
        "duration": {
          "value": "",
          "sustained": false
        },
        "damage": {
          "0": {
            "applyMod": false,
            "category": null,
            "formula": "1d4+1",
            "kinds": [
              "damage"
            ],
            "materials": [],
            "type": "force"
          }
        },
        "defense": null,
        "cost": {
          "value": ""
        },
        "location": {
          "value": "YuejnaqH1UUSFEtm",
          "heightenedLevel": 1
        },
        "counteraction": false,
        "overlays": {}
      },
      "type": "spell",
      "_stats": {
        "compendiumSource": "Compendium.pf2e.spells-srd.Item.gKKqvLohtrSJj3BM",
        "duplicateSource": null,
        "coreVersion": "12.331",
        "systemId": "pf2e",
        "systemVersion": "6.7.2"
      },
      "effects": [],
      "folder": null,
      "ownership": {
        "default": 0
      },
      "_key": "!actors.items!ePa0KmNPpR4zUPfX.LJv30DGfMEFT9EHc"
    },
    {
      "_id": "p7M7UC9dplhPVlfb",
      "flags": {
        "core": {
          "sourceId": "Compendium.pf2e.spells-srd.Item.vLzFcIaSXs7YTIqJ"
        }
      },
      "img": "systems/pf2e/icons/spells/message.webp",
      "name": "Message",
      "sort": 2000000,
      "system": {
        "description": {
          "gm": "",
          "value": "<p>You mouth words quietly, but instead of coming out of your mouth, they're transferred directly to the ears of the target. While others can't hear your words any better than if you normally mouthed them, the target can hear your words as if they were standing next to you.</p>\n<p>The target can give a brief response as a reaction, or as a free action on their next turn if they wish, but they must be able to see you and be within range to do so. If they respond, their response is delivered directly to your ear, just like the original message.</p>\n<hr />\n<p><strong>Heightened (3rd)</strong> The spell's range increases to 500 feet.</p>"
        },
        "rules": [],
        "slug": "message",
        "_migration": {
          "version": 0.935,
          "lastMigration": null,
          "previous": {
            "schema": 0.932,
            "foundry": "12.331",
            "system": "6.7.2"
          }
        },
        "traits": {
          "otherTags": [],
          "value": [
            "auditory",
            "cantrip",
            "concentrate",
            "illusion",
            "linguistic",
            "mental"
          ],
          "rarity": "common",
          "traditions": [
            "arcane",
            "divine",
            "occult"
          ]
        },
        "publication": {
          "title": "Pathfinder Core Rulebook",
          "authors": "",
          "license": "OGL",
          "remaster": false
        },
        "level": {
          "value": 1
        },
        "requirements": "",
        "target": {
          "value": "1 creature"
        },
        "range": {
          "value": "120 feet"
        },
        "area": null,
        "time": {
          "value": "1"
        },
        "duration": {
          "value": "see below",
          "sustained": false
        },
        "damage": {},
        "defense": null,
        "cost": {
          "value": ""
        },
        "location": {
          "value": "YuejnaqH1UUSFEtm"
        },
        "counteraction": false,
        "heightening": {
          "levels": {
            "3": {
              "range": {
                "value": "500 feet"
              }
            }
          },
          "type": "fixed"
        }
      },
      "type": "spell",
      "_stats": {
        "compendiumSource": "Compendium.pf2e.spells-srd.Item.vLzFcIaSXs7YTIqJ",
        "duplicateSource": null,
        "coreVersion": "12.331",
        "systemId": "pf2e",
        "systemVersion": "6.7.2"
      },
      "effects": [],
      "folder": null,
      "ownership": {
        "default": 0
      },
      "_key": "!actors.items!ePa0KmNPpR4zUPfX.p7M7UC9dplhPVlfb"
    },
    {
      "_id": "zXqiG5p6MwIqhfOo",
      "flags": {
        "core": {
          "sourceId": "Compendium.pf2e.spells-srd.Item.R8bqnYiThB6MYTxD"
        }
      },
      "img": "icons/magic/unholy/strike-beam-blood-small-red-purple.webp",
      "name": "Phantom Pain",
      "sort": 2100000,
      "system": {
        "description": {
          "gm": "",
          "value": "<p>Illusory pain wracks the target, dealing 2d4 mental damage and 1d4 persistent mental damage. The target must attempt a Will save.</p>\n<hr />\n<p><strong>Critical Success</strong> The target is unaffected.</p>\n<p><strong>Success</strong> The target takes full initial damage but no persistent damage, and the spell ends immediately.</p>\n<p><strong>Failure</strong> The target takes full initial and persistent damage, and the target is @UUID[Compendium.pf2e.conditionitems.Item.fesd1n5eVhpCSS18]{Sickened 1}. If the target recovers from being Sickened, the persistent damage ends and the spell ends.</p>\n<p><strong>Critical Failure</strong> As failure, but the target is @UUID[Compendium.pf2e.conditionitems.Item.fesd1n5eVhpCSS18]{Sickened 2}.</p>\n<hr />\n<p><strong>Heightened (+1)</strong> The damage increases by 2d4 and the persistent damage by 1d4.</p>\n<p>[[/r (@item.level)d4[persistent,mental]]]{Leveled Persistent Mental Damage}</p>"
        },
        "rules": [],
        "slug": "phantom-pain",
        "_migration": {
          "version": 0.935,
          "lastMigration": null,
          "previous": {
            "schema": 0.932,
            "foundry": "12.331",
            "system": "6.7.2"
          }
        },
        "traits": {
          "otherTags": [],
          "value": [
            "concentrate",
            "illusion",
            "manipulate",
            "mental",
            "nonlethal"
          ],
          "rarity": "common",
          "traditions": [
            "occult"
          ]
        },
        "publication": {
          "title": "Pathfinder Core Rulebook",
          "authors": "",
          "license": "OGL",
          "remaster": false
        },
        "level": {
          "value": 1
        },
        "requirements": "",
        "target": {
          "value": "1 creature"
        },
        "range": {
          "value": "30 feet"
        },
        "area": null,
        "time": {
          "value": "2"
        },
        "duration": {
          "value": "1 minute",
          "sustained": false
        },
        "damage": {
          "0": {
            "applyMod": false,
            "category": null,
            "formula": "2d4",
            "kinds": [
              "damage"
            ],
            "materials": [],
            "type": "mental"
          }
        },
        "defense": {
          "save": {
            "basic": false,
            "statistic": "will"
          }
        },
        "cost": {
          "value": ""
        },
        "location": {
          "value": "YuejnaqH1UUSFEtm",
          "heightenedLevel": 1
        },
        "counteraction": false,
        "heightening": {
          "damage": {
            "0": "2d4"
          },
          "interval": 1,
          "type": "interval"
        }
      },
      "type": "spell",
      "_stats": {
        "compendiumSource": "Compendium.pf2e.spells-srd.Item.R8bqnYiThB6MYTxD",
        "duplicateSource": null,
        "coreVersion": "12.331",
        "systemId": "pf2e",
        "systemVersion": "6.7.2"
      },
      "effects": [],
      "folder": null,
      "ownership": {
        "default": 0
      },
      "_key": "!actors.items!ePa0KmNPpR4zUPfX.zXqiG5p6MwIqhfOo"
    },
    {
      "_id": "T5RTOEKfn1xH57j3",
      "flags": {
        "core": {
          "sourceId": "Compendium.pf2e.spells-srd.Item.szIyEsvihc5e1w8n"
        }
      },
      "img": "icons/magic/air/air-burst-spiral-teal-green.webp",
      "name": "Soothe",
      "sort": 2200000,
      "system": {
        "description": {
          "gm": "",
          "value": "<p>You grace the target's mind, boosting its mental defenses and healing its wounds. The target regains 1d10+4 Hit Points when you Cast the Spell and gains a +2 status bonus to saves against mental effects for the duration.</p>\n<p>@UUID[Compendium.pf2e.spell-effects.Item.nkk4O5fyzrC0057i]{Spell Effect: Soothe}</p>\n<hr />\n<p><strong>Heightened (+1)</strong> The amount of healing increases by 1d10+4.</p>"
        },
        "rules": [],
        "slug": "soothe",
        "_migration": {
          "version": 0.935,
          "lastMigration": null,
          "previous": {
            "schema": 0.932,
            "foundry": "12.331",
            "system": "6.7.2"
          }
        },
        "traits": {
          "otherTags": [],
          "value": [
            "concentrate",
            "emotion",
            "healing",
            "manipulate",
            "mental"
          ],
          "rarity": "common",
          "traditions": [
            "occult"
          ]
        },
        "publication": {
          "title": "Pathfinder Core Rulebook",
          "authors": "",
          "license": "OGL",
          "remaster": false
        },
        "level": {
          "value": 1
        },
        "requirements": "",
        "target": {
          "value": "1 willing creature"
        },
        "range": {
          "value": "30 feet"
        },
        "area": null,
        "time": {
          "value": "2"
        },
        "duration": {
          "value": "1 minute",
          "sustained": false
        },
        "damage": {
          "0": {
            "applyMod": false,
            "category": null,
            "formula": "1d10+4",
            "kinds": [
              "healing"
            ],
            "materials": [],
            "type": "untyped"
          }
        },
        "defense": null,
        "cost": {
          "value": ""
        },
        "location": {
          "value": "YuejnaqH1UUSFEtm",
          "heightenedLevel": 1
        },
        "counteraction": false,
        "heightening": {
          "damage": {
            "0": "1d10+4"
          },
          "interval": 1,
          "type": "interval"
        }
      },
      "type": "spell",
      "_stats": {
        "compendiumSource": "Compendium.pf2e.spells-srd.Item.szIyEsvihc5e1w8n",
        "duplicateSource": null,
        "coreVersion": "12.331",
        "systemId": "pf2e",
        "systemVersion": "6.7.2"
      },
      "effects": [],
      "folder": null,
      "ownership": {
        "default": 0
      },
      "_key": "!actors.items!ePa0KmNPpR4zUPfX.T5RTOEKfn1xH57j3"
    },
    {
      "_id": "7IjR4hMNtoS1jTfK",
      "flags": {
        "core": {
          "sourceId": "Compendium.pf2e.equipment-srd.Item.YnPYSKCQBLIOtm0J"
        }
      },
      "img": "systems/pf2e/icons/equipment/weapons/aklys.webp",
      "name": "Aklys",
      "sort": 2300000,
      "system": {
        "description": {
          "gm": "",
          "value": "<p>The aklys is a throwing club with a hook on one end and a lengthy cord attached to the other. Though aklyses aren't available in most shops, one might be purchased for 5 gp from a vendor that specializes in strange weapons.</p>"
        },
        "rules": [],
        "slug": "aklys",
        "_migration": {
          "version": 0.935,
          "lastMigration": null,
          "previous": {
            "schema": 0.932,
            "foundry": "12.331",
            "system": "6.7.2"
          }
        },
        "traits": {
          "otherTags": [],
          "value": [
            "ranged-trip",
            "tethered",
            "thrown-20",
            "trip"
          ],
          "rarity": "uncommon"
        },
        "publication": {
          "title": "Pathfinder Bestiary",
          "authors": "",
          "license": "OGL",
          "remaster": false
        },
        "level": {
          "value": 0
        },
        "quantity": 1,
        "baseItem": "aklys",
        "bulk": {
          "value": 1
        },
        "hp": {
          "value": 0,
          "max": 0
        },
        "hardness": 0,
        "price": {
          "value": {
            "gp": 5
          }
        },
        "equipped": {
          "carryType": "held",
          "invested": null,
          "handsHeld": 1
        },
        "containerId": null,
        "size": "med",
        "material": {
          "type": null,
          "grade": null
        },
        "identification": {
          "status": "identified",
          "unidentified": {
            "name": "",
            "img": "",
            "data": {
              "description": {
                "value": ""
              }
            }
          },
          "misidentified": {}
        },
        "usage": {
          "value": "held-in-one-hand"
        },
        "category": "advanced",
        "group": "club",
        "bonus": {
          "value": 0
        },
        "damage": {
          "dice": 1,
          "die": "d6",
          "damageType": "bludgeoning",
          "persistent": null
        },
        "bonusDamage": {
          "value": 0
        },
        "splashDamage": {
          "value": null
        },
        "range": null,
        "reload": {
          "value": "-"
        },
        "runes": {
          "potency": 0,
          "striking": 0,
          "property": []
        },
        "specific": null,
        "subitems": [],
        "property1": {
          "value": "",
          "dice": 0,
          "die": "",
          "damageType": "",
          "critDice": 0,
          "critDie": "",
          "critDamage": "",
          "critDamageType": ""
        }
      },
      "type": "weapon",
      "_stats": {
        "compendiumSource": "Compendium.pf2e.equipment-srd.Item.YnPYSKCQBLIOtm0J",
        "duplicateSource": null,
        "coreVersion": "12.331",
        "systemId": "pf2e",
        "systemVersion": "6.7.2"
      },
      "effects": [],
      "folder": null,
      "ownership": {
        "default": 0
      },
      "_key": "!actors.items!ePa0KmNPpR4zUPfX.7IjR4hMNtoS1jTfK"
    },
    {
      "_id": "6N6oDDqKb0CaILEx",
      "flags": {
        "pf2e": {
          "linkedWeapon": "7IjR4hMNtoS1jTfK"
        }
      },
      "img": "systems/pf2e/icons/default-icons/melee.svg",
      "name": "Aklys",
      "sort": 2400000,
      "system": {
        "attackEffects": {
          "value": []
        },
        "bonus": {
          "value": 10
        },
        "damageRolls": {
          "ljdligppovb6ee2ngfkp": {
            "damage": "1d6+3",
            "damageType": "bludgeoning",
            "category": null
          }
        },
        "description": {
          "value": "",
          "gm": ""
        },
        "publication": {
          "license": "OGL",
          "remaster": false,
          "title": "",
          "authors": ""
        },
        "rules": [],
        "slug": null,
        "traits": {
          "value": [
            "trip"
          ],
          "otherTags": []
        },
        "_migration": {
          "version": 0.935,
          "previous": {
            "schema": 0.932,
            "foundry": "12.331",
            "system": "6.7.2"
          }
        }
      },
      "type": "melee",
      "_stats": {
        "compendiumSource": null,
        "duplicateSource": null,
        "coreVersion": "12.331",
        "systemId": "pf2e",
        "systemVersion": "6.7.2"
      },
      "effects": [],
      "folder": null,
      "ownership": {
        "default": 0
      },
      "_key": "!actors.items!ePa0KmNPpR4zUPfX.6N6oDDqKb0CaILEx"
    },
    {
      "_id": "saoVl2MlopNbuTo8",
      "flags": {
        "pf2e": {
          "linkedWeapon": "7IjR4hMNtoS1jTfK"
        }
      },
      "img": "systems/pf2e/icons/default-icons/melee.svg",
      "name": "Aklys",
      "sort": 2500000,
      "system": {
        "attackEffects": {
          "value": []
        },
        "bonus": {
          "value": 13
        },
        "damageRolls": {
          "gc4xnalxd9nv71da2yyy": {
            "damage": "1d6+3",
            "damageType": "bludgeoning",
            "category": null
          }
        },
        "description": {
          "value": "",
          "gm": ""
        },
        "publication": {
          "license": "OGL",
          "remaster": false,
          "title": "",
          "authors": ""
        },
        "rules": [],
        "slug": null,
        "traits": {
          "value": [
            "ranged-trip",
            "tethered",
            "thrown-20"
          ],
          "otherTags": []
        },
        "_migration": {
          "version": 0.935,
          "previous": {
            "schema": 0.932,
            "foundry": "12.331",
            "system": "6.7.2"
          }
        }
      },
      "type": "melee",
      "_stats": {
        "compendiumSource": null,
        "duplicateSource": null,
        "coreVersion": "12.331",
        "systemId": "pf2e",
        "systemVersion": "6.7.2"
      },
      "effects": [],
      "folder": null,
      "ownership": {
        "default": 0
      },
      "_key": "!actors.items!ePa0KmNPpR4zUPfX.saoVl2MlopNbuTo8"
    },
    {
      "_id": "qtsF75k2Zterahrt",
      "img": "systems/pf2e/icons/actions/Passive.webp",
      "name": "Vulnerable to Sunlight",
      "sort": 2600000,
      "system": {
        "description": {
          "gm": "",
          "value": "<p>A dero magister takes [[/r {10}]]{10 damage} for every hour they're exposed to sunlight.</p>"
        },
        "rules": [],
        "slug": null,
        "_migration": {
          "version": 0.935,
          "previous": {
            "schema": 0.932,
            "foundry": "12.331",
            "system": "6.7.2"
          }
        },
        "traits": {
          "otherTags": [],
          "value": []
        },
        "publication": {
          "title": "",
          "authors": "",
          "license": "OGL",
          "remaster": false
        },
        "actionType": {
          "value": "passive"
        },
        "category": "defensive",
        "actions": {
          "value": null
        },
        "deathNote": false
      },
      "type": "action",
      "_stats": {
        "compendiumSource": null,
        "duplicateSource": null,
        "coreVersion": "12.331",
        "systemId": "pf2e",
        "systemVersion": "6.7.2"
      },
      "effects": [],
      "folder": null,
      "ownership": {
        "default": 0
      },
      "flags": {},
      "_key": "!actors.items!ePa0KmNPpR4zUPfX.qtsF75k2Zterahrt"
    },
    {
      "_id": "36QKwrAooz1cygR4",
      "img": "systems/pf2e/icons/actions/OneAction.webp",
      "name": "Cytillesh Stare",
      "sort": 2700000,
      "system": {
        "description": {
          "gm": "",
          "value": "<p><strong>Frequency</strong> once per round</p>\n<hr />\n<p><strong>Effect</strong> The magister focuses their gaze on a creature they can see within 30 feet. The target is @UUID[Compendium.pf2e.conditionitems.Item.TkIyaNPgTZFBCCuh]{Dazzled} for 1 round and must succeed at a @Check[type:will|dc:24] saving throw or be @UUID[Compendium.pf2e.conditionitems.Item.yblD8fOR1J8rDwEQ]{Confused} for 1 round.</p>"
        },
        "rules": [],
        "slug": null,
        "_migration": {
          "version": 0.935,
          "previous": {
            "schema": 0.932,
            "foundry": "12.331",
            "system": "6.7.2"
          }
        },
        "traits": {
          "otherTags": [],
          "value": [
            "concentrate",
            "incapacitation",
            "mental",
            "visual"
          ]
        },
        "publication": {
          "title": "",
          "authors": "",
          "license": "OGL",
          "remaster": false
        },
        "actionType": {
          "value": "action"
        },
        "category": "offensive",
        "actions": {
          "value": 1
        },
        "deathNote": false,
        "frequency": {
          "max": 1,
          "per": "round",
          "value": 1
        }
      },
      "type": "action",
      "_stats": {
        "compendiumSource": null,
        "duplicateSource": null,
        "coreVersion": "12.331",
        "systemId": "pf2e",
        "systemVersion": "6.7.2"
      },
      "effects": [],
      "folder": null,
      "ownership": {
        "default": 0
      },
      "flags": {},
      "_key": "!actors.items!ePa0KmNPpR4zUPfX.36QKwrAooz1cygR4"
    }
  ],
  "name": "Dero Magister",
  "system": {
    "attributes": {
      "hp": {
        "value": 65,
        "temp": 0,
        "max": 65,
        "details": ""
      },
      "speed": {
        "value": 20,
        "otherSpeeds": [],
        "details": ""
      },
      "ac": {
        "value": 22,
        "details": ""
      },
      "allSaves": {
        "value": ""
      },
      "weaknesses": [
        {
          "type": "vulnerable-to-sunlight",
          "value": 0
        }
      ]
    },
    "initiative": {
      "statistic": "perception"
    },
    "details": {
      "languages": {
        "value": [
          "aklo",
          "sakvroth"
        ],
        "details": ""
      },
      "level": {
        "value": 5
      },
      "blurb": "",
      "publicNotes": "<p>Dero magisters are leaders among dero society. They perform the bulk of the cruel operations and memory-altering procedures inflicted upon their victims.</p>\n<hr />\n<p>Deros are short, wiry humanoids with milky white eyes, gray-blue skin, and wild shocks of off-white or gray hair. The descendants of a mysterious type of fey abandoned in the deepest, darkest caverns of Golarion, deros are the subject of fearful legends and folk tales to most of the world's surface races. They skulk beneath major metropolitan areas, performing cruel and twisted experiments on unwilling subjects. A dero is 3 feet tall and weighs approximately 70 pounds.</p>",
      "privateNotes": "",
      "publication": {
        "title": "Pathfinder Bestiary",
        "authors": "",
        "license": "OGL",
        "remaster": false
      }
    },
    "resources": {
      "focus": {
        "max": 1,
        "value": 1
      }
    },
    "_migration": {
      "version": 0.935,
      "previous": {
        "schema": 0.932,
        "foundry": "12.331",
        "system": "6.7.2"
      }
    },
    "abilities": {
      "str": {
        "mod": 1
      },
      "dex": {
        "mod": 4
      },
      "con": {
        "mod": 2
      },
      "int": {
        "mod": 3
      },
      "wis": {
        "mod": -1
      },
      "cha": {
        "mod": 5
      }
    },
    "perception": {
      "details": "",
      "mod": 8,
      "senses": [
        {
          "type": "darkvision"
        }
      ],
      "vision": true
    },
    "saves": {
      "fortitude": {
        "value": 10,
        "saveDetail": ""
      },
      "reflex": {
        "value": 13,
        "saveDetail": ""
      },
      "will": {
        "value": 10,
        "saveDetail": ""
      }
    },
    "skills": {
      "crafting": {
        "base": 12
      },
      "medicine": {
        "base": 8
      },
      "occultism": {
        "base": 12
      },
      "stealth": {
        "base": 11
      }
    },
    "traits": {
      "value": [
        "chaotic",
        "dero",
        "evil",
        "humanoid"
      ],
      "rarity": "uncommon",
      "size": {
        "value": "sm"
      }
    }
  },
  "type": "npc",
  "_stats": {
    "compendiumSource": "Compendium.pf2e.pathfinder-bestiary.Actor.ePa0KmNPpR4zUPfX",
    "duplicateSource": null,
    "coreVersion": "12.331",
    "systemId": "pf2e",
    "systemVersion": "6.7.2"
  },
  "flags": {
    "core": {
      "sourceId": "Compendium.pf2e.pathfinder-bestiary.Actor.ePa0KmNPpR4zUPfX"
    }
  },
  "effects": [],
  "ownership": {
    "default": 0,
    "Yb7GAnhzVbd5I9T9": 3
  },
  "sort": 0,
  "_key": "!actors!ePa0KmNPpR4zUPfX"
}