{
  "_id": "IOcjPmcemrQFFb2b",
  "img": "systems/pf2e/icons/default-icons/background.svg",
  "name": "Time Traveler",
  "system": {
    "description": {
      "gm": "",
      "value": "<p>You come from a different time. Whether by your own doing or a terrible accident, powerful magic has resulted in you coming to this time from the future or from the past, but you are unable to return. You might be from New Thassilon, an entire nation of time travelers.</p>\n<p>Choose two ability boosts. One must be to <strong>Dexterity</strong> or <strong>Intelligence</strong>, and one is a free ability boost.</p>\n<p>You are trained in three Lore skills of your choice that represent your knowledge from your old time. You gain the @UUID[Compendium.pf2e.actionspf2e.Item.3cuTA58ObXhuFX2r]{Bend Time} reaction.</p>"
    },
    "rules": [
      {
        "key": "GrantItem",
        "uuid": "Compendium.pf2e.actionspf2e.Item.3cuTA58ObXhuFX2r"
      }
    ],
    "slug": "time-traveler",
    "_migration": {
      "version": 0.935,
      "lastMigration": null,
      "previous": {
        "schema": 0.879,
        "foundry": "12.331",
        "system": "6.7.2"
      }
    },
    "traits": {
      "otherTags": [],
      "value": [],
      "rarity": "rare"
    },
    "publication": {
      "title": "Pathfinder Secrets of Magic",
      "authors": "",
      "license": "OGL",
      "remaster": false
    },
    "boosts": {
      "0": {
        "value": [
          "dex",
          "int"
        ]
      },
      "1": {
        "value": [
          "cha",
          "con",
          "dex",
          "int",
          "str",
          "wis"
        ]
      }
    },
    "items": {},
    "trainedSkills": {
      "value": [],
      "lore": [
        "<Three Different> Lore"
      ]
    }
  },
  "type": "background",
  "flags": {
    "core": {
      "sourceId": "Compendium.pf2e.backgrounds.Item.IOcjPmcemrQFFb2b"
    }
  },
  "effects": [],
  "_stats": {
    "coreVersion": "12.331",
    "systemId": "pf2e",
    "systemVersion": "6.7.2",
    "compendiumSource": "Compendium.pf2e-legacy-content.backgrounds-legacy.Item.IOcjPmcemrQFFb2b",
    "duplicateSource": null
  },
  "folder": null,
  "sort": 0,
  "ownership": {
    "default": 0
  },
  "_key": "!items!IOcjPmcemrQFFb2b"
}
