{
  "_id": "UgoM6FBiZfc7KqCV",
  "img": "icons/magic/defensive/armor-stone-skin.webp",
  "name": "Effect: Curse of Stone",
  "system": {
    "description": {
      "gm": "",
      "value": "<p>The creature gains a +1 status bonus to its AC.</p>"
    },
    "rules": [
      {
        "key": "FlatModifier",
        "selector": "ac",
        "type": "status",
        "value": 1
      }
    ],
    "slug": "effect-curse-of-stone",
    "_migration": {
      "version": 0.935,
      "lastMigration": null,
      "previous": {
        "schema": 0.879,
        "foundry": "12.331",
        "system": "6.7.2"
      }
    },
    "traits": {
      "otherTags": [],
      "value": [],
      "rarity": "common"
    },
    "publication": {
      "title": "Pathfinder Lost Omens: Impossible Lands",
      "authors": "",
      "license": "OGL",
      "remaster": false
    },
    "level": {
      "value": 1
    },
    "duration": {
      "value": -1,
      "unit": "unlimited",
      "expiry": null,
      "sustained": false
    },
    "start": {
      "value": 0,
      "initiative": null
    },
    "tokenIcon": {
      "show": true
    },
    "badge": null,
    "context": null
  },
  "type": "effect",
  "flags": {
    "core": {
      "sourceId": "Compendium.pf2e.bestiary-effects.Item.UgoM6FBiZfc7KqCV"
    }
  },
  "effects": [],
  "_stats": {
    "coreVersion": "12.331",
    "systemId": "pf2e",
    "systemVersion": "6.7.2",
    "compendiumSource": "Compendium.pf2e-legacy-content.bestiary-effects-legacy.Item.UgoM6FBiZfc7KqCV",
    "duplicateSource": null
  },
  "folder": null,
  "sort": 0,
  "ownership": {
    "default": 0
  },
  "_key": "!items!UgoM6FBiZfc7KqCV"
}
