{
  "_id": "exwQF6E1FWmuxwBc",
  "img": "systems/pf2e/icons/equipment/vehicles/vonthoss-golden-bridge-protective-barrier-effect.webp",
  "name": "Effect: Protective Barrier",
  "system": {
    "description": {
      "gm": "",
      "value": "<p>Granted by Vontho's Golden Bridge</p>\n<p>While the swirling rings of the vehicle don't fully cover the pilot, they offer incredible protection, magically maintaining the temperature within and ablating physical attacks. The pilot is protected from severe cold, severe heat, extreme cold, and extreme heat. The pilot also gains resistance 10 to all physical damage (except adamantine).</p>"
    },
    "rules": [
      {
        "exceptions": [
          "adamantine"
        ],
        "key": "Resistance",
        "type": "all-damage",
        "value": 10
      }
    ],
    "slug": "effect-protective-barrier",
    "_migration": {
      "version": 0.935,
      "lastMigration": null,
      "previous": {
        "schema": 0.879,
        "foundry": "12.331",
        "system": "6.7.2"
      }
    },
    "traits": {
      "otherTags": [],
      "value": [],
      "rarity": "common"
    },
    "publication": {
      "title": "Pathfinder Guns & Gears",
      "authors": "",
      "license": "OGL",
      "remaster": false
    },
    "level": {
      "value": 17
    },
    "duration": {
      "value": -1,
      "unit": "unlimited",
      "expiry": null,
      "sustained": false
    },
    "start": {
      "value": 0,
      "initiative": null
    },
    "tokenIcon": {
      "show": true
    },
    "badge": null,
    "context": null
  },
  "type": "effect",
  "flags": {
    "core": {
      "sourceId": "Compendium.pf2e.equipment-effects.Item.exwQF6E1FWmuxwBc"
    }
  },
  "effects": [],
  "_stats": {
    "coreVersion": "12.331",
    "systemId": "pf2e",
    "systemVersion": "6.7.2",
    "compendiumSource": "Compendium.pf2e-legacy-content.equipment-effects-legacy.Item.exwQF6E1FWmuxwBc",
    "duplicateSource": null
  },
  "folder": null,
  "sort": 0,
  "ownership": {
    "default": 0
  },
  "_key": "!items!exwQF6E1FWmuxwBc"
}
